{"solana": [{"address": {"address": "9MdQa4in4UzwGGsyfqZSJoqbNVM4qF4zESQYkxS8tw3T", "chain": "solana", "isUserAddress": false, "ownerAddress": {"address": "7Jf1DBJYwiaZ6rm6rb7ddp5A7SiLuArc5TyqfF73fTkb", "chain": "solana", "isUserAddress": false, "program": false}}, "usd": 196.25774842500687, "transactionCount": 169, "flow": "all", "chains": ["solana"]}, {"address": {"address": "3JqxpX4P8QZpUnN2HZUTR6qMrurKeGQ3FzsgNnwhRZbj", "chain": "solana", "isUserAddress": false, "ownerAddress": {"address": "Hc8nNmo4YZEcioRa67mzzgQae2SRkFNDEtYYponWbd2", "chain": "solana", "isUserAddress": false, "program": false}}, "usd": 20.15999984741211, "transactionCount": 1, "flow": "in", "chains": ["solana"]}]}