{"solana": [{"address": {"address": "9MkixYmjT2UbMgnNnPBTYkRjzdmi4zP1jkMdCkR89L67", "chain": "solana", "arkhamEntity": {"name": "ZeroFi", "note": "", "id": "zerofi", "type": "dex", "service": null, "addresses": null}, "arkhamLabel": {"name": "Vault", "address": "9MkixYmjT2UbMgnNnPBTYkRjzdmi4zP1jkMdCkR89L67", "chainType": "solana"}, "isUserAddress": false, "ownerAddress": {"address": "9MkixYmjT2UbMgnNnPBTYkRjzdmi4zP1jkMdCkR89L67", "chain": "solana", "arkhamEntity": {"name": "ZeroFi", "note": "", "id": "zerofi", "type": "dex", "service": null, "addresses": null}, "arkhamLabel": {"name": "Vault", "address": "9MkixYmjT2UbMgnNnPBTYkRjzdmi4zP1jkMdCkR89L67", "chainType": "solana"}, "isUserAddress": false, "service": false, "program": false}}, "usd": 46695.66794947708, "transactionCount": 571, "flow": "all", "chains": ["solana"]}, {"address": {"address": "CQCiSTBFmKHtX1XKxhmLwTqxC3y9zGRmo787GNSoXHt1", "chain": "solana", "isUserAddress": false, "ownerAddress": {"address": "fx4E7VEysZciM5nqNbCeEUYPzfYSStuz19SWskTqxnk", "chain": "solana", "isUserAddress": false, "program": false}}, "usd": 45250, "transactionCount": 1, "flow": "in", "chains": ["solana"]}, {"address": {"address": "4dmvFGeQH2eqa3ktNHMgm4wZ8vuTukBiK9M7gxW5oR9F", "chain": "solana", "arkhamEntity": {"name": "Orca", "note": "", "id": "orca", "type": "dex", "service": null, "addresses": null, "website": "https://www.orca.so", "twitter": "https://x.com/orca_so"}, "arkhamLabel": {"name": "Pool", "address": "4dmvFGeQH2eqa3ktNHMgm4wZ8vuTukBiK9M7gxW5oR9F", "chainType": "solana"}, "isUserAddress": false, "ownerAddress": {"address": "5zpyutJu9ee6jFymDGoK7F6S5Kczqtc9FomP3ueKuyA9", "chain": "solana", "arkhamEntity": {"name": "Orca", "note": "", "id": "orca", "type": "dex", "service": null, "addresses": null, "website": "https://www.orca.so", "twitter": "https://x.com/orca_so"}, "arkhamLabel": {"name": "Market", "address": "5zpyutJu9ee6jFymDGoK7F6S5Kczqtc9FomP3ueKuyA9", "chainType": "solana"}, "isUserAddress": false, "service": false, "program": false}}, "usd": 19685.406105326954, "transactionCount": 225, "flow": "all", "chains": ["solana"]}, {"address": {"address": "9B67BXnxvwSb4XxPedmURbuciYHtnX7EmbVMeNGHCB4C", "chain": "solana", "arkhamEntity": {"name": "Meteora (Prev. Mercurial)", "note": "", "id": "meteora", "type": "dex", "service": null, "addresses": null, "website": "https://www.meteora.ag", "twitter": "https://x.com/MeteoraAG"}, "arkhamLabel": {"name": "Pool", "address": "9B67BXnxvwSb4XxPedmURbuciYHtnX7EmbVMeNGHCB4C", "chainType": "solana"}, "isUserAddress": false, "ownerAddress": {"address": "4UcZrPsyYVaY4Rt4ebCPwEyxn1VAhw5nXhF3e3PGCB4v", "chain": "solana", "arkhamEntity": {"name": "Meteora (Prev. Mercurial)", "note": "", "id": "meteora", "type": "dex", "service": null, "addresses": null, "website": "https://www.meteora.ag", "twitter": "https://x.com/MeteoraAG"}, "arkhamLabel": {"name": "Market", "address": "4UcZrPsyYVaY4Rt4ebCPwEyxn1VAhw5nXhF3e3PGCB4v", "chainType": "solana"}, "isUserAddress": false, "service": false, "program": false}}, "usd": 17417.035561078716, "transactionCount": 11, "flow": "all", "chains": ["solana"]}, {"address": {"address": "DDSpWmWt4KWV6gZb2q3pMp6rBeQhemaJpFPQDsCgtX5G", "chain": "solana", "isUserAddress": false, "ownerAddress": {"address": "DcdWv2Whi4eVT9sXNz65MJL5qXahhCRY8y8nsAJ1jd48", "chain": "solana", "isUserAddress": false, "program": false}}, "usd": 5821.140625, "transactionCount": 1, "flow": "out", "chains": ["solana"]}, {"address": {"address": "62yyadnjwodqqyx8R4AQ338o5g5bBG7Zbu5GaTycAiG4", "chain": "solana", "isUserAddress": false, "ownerAddress": {"address": "DP6KGQmqMjBBysqzKwMPyY9Xi4tSwHU9BspNZraF6JFb", "chain": "solana", "isUserAddress": false, "program": false}}, "usd": 2988.263671875, "transactionCount": 1, "flow": "out", "chains": ["solana"]}, {"address": {"address": "mVUFC1jjSX7CofxvbKroQMPLVq91tZYn1sotFpzNgZN", "chain": "solana", "isUserAddress": false, "ownerAddress": {"address": "BU4fWsDGcsqkJfzzhuBUZk4k8R9bjwLj9Dt4duzki6P1", "chain": "solana", "isUserAddress": false, "program": false}}, "usd": 2635.1341574192047, "transactionCount": 2, "flow": "in", "chains": ["solana"]}, {"address": {"address": "CkVvH4RRtWxi9c1NeWNooWamxPeYATM38Db87Ez7Si3K", "chain": "solana", "isUserAddress": false, "ownerAddress": {"address": "9XextR3cEguFRxS4DeJA52QxiM5pzLw9atz9eikVYVgy", "chain": "solana", "isUserAddress": false, "program": false}}, "usd": 2517.3354778289795, "transactionCount": 19, "flow": "all", "chains": ["solana"]}, {"address": {"address": "5zX5yCDPQVrRBWhSBcgaotNySUsyxcWGMhd6VRSdRAf1", "chain": "solana", "isUserAddress": false, "ownerAddress": {"address": "8XvJxDLxzv8cFqSrgPJfwjNLgqXpdBmSdHVa7CYfx5Yj", "chain": "solana", "isUserAddress": false, "program": false}}, "usd": 2283.600006341934, "transactionCount": 4, "flow": "in", "chains": ["solana"]}, {"address": {"address": "D4uJ9ASY1y1qsQ8g4vgv7V514VVsBK5sdAVJkSYqLYPj", "chain": "solana", "arkhamEntity": {"name": "Meteora (Prev. Mercurial)", "note": "", "id": "meteora", "type": "dex", "service": null, "addresses": null, "website": "https://www.meteora.ag", "twitter": "https://x.com/MeteoraAG"}, "arkhamLabel": {"name": "Pool", "address": "D4uJ9ASY1y1qsQ8g4vgv7V514VVsBK5sdAVJkSYqLYPj", "chainType": "solana"}, "isUserAddress": false, "ownerAddress": {"address": "6oFWm7KPLfxnwMb3z5xwBoXNSPP3JJyirAPqPSiVcnsp", "chain": "solana", "arkhamEntity": {"name": "Meteora (Prev. Mercurial)", "note": "", "id": "meteora", "type": "dex", "service": null, "addresses": null, "website": "https://www.meteora.ag", "twitter": "https://x.com/MeteoraAG"}, "arkhamLabel": {"name": "Market", "address": "6oFWm7KPLfxnwMb3z5xwBoXNSPP3JJyirAPqPSiVcnsp", "chainType": "solana"}, "isUserAddress": false, "service": false, "program": false}}, "usd": 2246.643616495654, "transactionCount": 88, "flow": "all", "chains": ["solana"]}, {"address": {"address": "8zE9ziG1D5uR9EN27uVTxCvA2bMBqGxeUjzyWK9ajou7", "chain": "solana", "isUserAddress": false, "ownerAddress": {"address": "5FtweMt2K5BDvGKpwwZfygaR259jmGSRGL8LDHd3KLaS", "chain": "solana", "isUserAddress": false, "program": false}}, "usd": 2130, "transactionCount": 2, "flow": "in", "chains": ["solana"]}, {"address": {"address": "7e2jpF3QRospec5tGsgxYZ5XsgcV3MZk6gJ7G7JVNaZe", "chain": "solana", "isUserAddress": false, "ownerAddress": {"address": "9BA2dqTMmwCshFDSs64ksA6kmzPQobvsK3R55nKHG8Eo", "chain": "solana", "isUserAddress": false, "program": false}}, "usd": 1814.0000351667404, "transactionCount": 2, "flow": "in", "chains": ["solana"]}, {"address": {"address": "8waUHd52GGvKK1yi3kwt57qkrHNpjdCfZorWb5hKxqk", "chain": "solana", "isUserAddress": false, "ownerAddress": {"address": "7abU5SFQ3pAeBo8GLftA7sr7zPoX8nRj2BxMC33XqX7L", "chain": "solana", "isUserAddress": false, "program": false}}, "usd": 1727.2502746582031, "transactionCount": 6, "flow": "all", "chains": ["solana"]}, {"address": {"address": "2eUCBFE3Gkgs9d4huRzEt27K6vkiCzA1S3pL43XbQbkJ", "chain": "solana", "isUserAddress": false, "ownerAddress": {"address": "Fx5gTS38fRACWA9NsYPBZPpSDxqqA6rC19LTW3dLV94N", "chain": "solana", "isUserAddress": false, "program": false}}, "usd": 1001.370361328125, "transactionCount": 1, "flow": "out", "chains": ["solana"]}, {"address": {"address": "9zaxE6eibamaoX47qnL88VAU6Ki9nwvwgMKSiepK7fLV", "chain": "solana", "isUserAddress": false, "ownerAddress": {"address": "if6RZbX2pJEsxaBDH1aFWvAaWUb3dLcouZ2onNXkj1F", "chain": "solana", "isUserAddress": false, "program": false}}, "usd": 1000.5711059570312, "transactionCount": 1, "flow": "out", "chains": ["solana"]}, {"address": {"address": "9oEEXmdLQYqJ3bEMAWXaDqfi6ZGipXBG9Ko11T9afy3n", "chain": "solana", "isUserAddress": false, "ownerAddress": {"address": "AGDFH4tgkn8dB1tUn4Zxtf6hkDqZCwUWHagsTNmmDaza", "chain": "solana", "isUserAddress": false, "program": false}}, "usd": 985.5264282226562, "transactionCount": 1, "flow": "out", "chains": ["solana"]}, {"address": {"address": "J9b5i8xb967s1Eg8X3pF6Z4uZWSXkppcTEow9GjpTcXz", "chain": "solana", "isUserAddress": false, "ownerAddress": {"address": "EJt5XG21QQk9RQbqNU2EsTvV3VscwHhaAde6joQRMy5o", "chain": "solana", "isUserAddress": false, "program": false}}, "usd": 709.6615658998489, "transactionCount": 2, "flow": "in", "chains": ["solana"]}, {"address": {"address": "Dawmf7dS9b89f37nDnVxbGPEiUQZn2HU5oPnzvzPH7aS", "chain": "solana", "isUserAddress": false, "ownerAddress": {"address": "286dsGdLVtYWXX3Pg1X4tTjeiYSnFyrteqQL2SC2hWZf", "chain": "solana", "isUserAddress": false, "program": false}}, "usd": 598.291259765625, "transactionCount": 6, "flow": "all", "chains": ["solana"]}, {"address": {"address": "4DVu2EL1QeMu9mhyhJq5nQ3bm7JUPkU8CRfNFhbCZP8g", "chain": "solana", "isUserAddress": false, "ownerAddress": {"address": "Fv7Vfo2cLGxZfKGaUzNZK4JE6az7ou6xQ69QhaMD4Yqa", "chain": "solana", "isUserAddress": false, "program": false}}, "usd": 595.3177490234375, "transactionCount": 1, "flow": "out", "chains": ["solana"]}, {"address": {"address": "BXNSvtqvsjWDbSkFYog2jjuigSzR39KrpXcXf8SETvyX", "chain": "solana", "isUserAddress": false, "ownerAddress": {"address": "3vjYPqMb3YyuzEMjSEAnhMfU48qjGoUNjuXjFDGqBFRm", "chain": "solana", "isUserAddress": false, "program": false}}, "usd": 581.5260460078716, "transactionCount": 8, "flow": "in", "chains": ["solana"]}, {"address": {"address": "7isSQYWRpUKrnrE1vPCxmnitwwkyZH3ouRytmdLpt2Da", "chain": "solana", "isUserAddress": false, "ownerAddress": {"address": "5nU89koeUibgDGrYLdBppGujzydY5vr5RYfbaWaeX79A", "chain": "solana", "isUserAddress": false, "program": false}}, "usd": 546.8933277130127, "transactionCount": 7, "flow": "all", "chains": ["solana"]}, {"address": {"address": "EgVLCKwvnysgxDSYbCYUUqCbch4Rk4bucYEarsEik7ud", "chain": "solana", "isUserAddress": false, "ownerAddress": {"address": "9wap3NtthZBDVxMgUs7Sjwp3oEHU8d8aPXLhkRWGqCDT", "chain": "solana", "isUserAddress": false, "program": false}}, "usd": 500.14239501953125, "transactionCount": 1, "flow": "out", "chains": ["solana"]}, {"address": {"address": "G2f4yJSrTn97qs8FCzwfTgU3n1qagKMBsyNoYPBrxN25", "chain": "solana", "isUserAddress": false, "ownerAddress": {"address": "U48zRqRLMNQr1SJX7ETMqxgxAq3irEV8XRG5jRAm1LX", "chain": "solana", "isUserAddress": false, "program": false}}, "usd": 462.2877502441406, "transactionCount": 1, "flow": "out", "chains": ["solana"]}, {"address": {"address": "DBW3ZfheSXEWzqcoUCy11dX4uazNbGTar7LmBMXReJpZ", "chain": "solana", "arkhamEntity": {"name": "BonkSwap", "note": "", "id": "bonkswap", "type": "dex", "service": null, "addresses": null, "website": "https://www.bonkswap.io/", "twitter": "https://x.com/bonkswap_io"}, "arkhamLabel": {"name": "Pool", "address": "DBW3ZfheSXEWzqcoUCy11dX4uazNbGTar7LmBMXReJpZ", "chainType": "solana"}, "isUserAddress": false, "ownerAddress": {"address": "8NyaPDJeC2eaBGpkRpZKnD9S448AZGgjSvumFe92DRK2", "chain": "solana", "arkhamEntity": {"name": "BonkSwap", "note": "", "id": "bonkswap", "type": "dex", "service": null, "addresses": null, "website": "https://www.bonkswap.io/", "twitter": "https://x.com/bonkswap_io"}, "arkhamLabel": {"name": "Vault Authority", "address": "8NyaPDJeC2eaBGpkRpZKnD9S448AZGgjSvumFe92DRK2", "chainType": "solana"}, "isUserAddress": false, "service": false, "program": false}}, "usd": 452.78318959474564, "transactionCount": 21, "flow": "all", "chains": ["solana"]}, {"address": {"address": "4GswkuXyM3ZJkWNNRRCAmFwgwiVNFjJ3H7mK24CAQWnr", "chain": "solana", "isUserAddress": false, "ownerAddress": {"address": "5PQdBKb3o2ZfYgscPb8YSxGx2AqtjfLt9cLU8TaBWsDf", "chain": "solana", "isUserAddress": false, "program": false}}, "usd": 423.1501998901367, "transactionCount": 8, "flow": "all", "chains": ["solana"]}, {"address": {"address": "7X8FC48gtWFewzFtu2jm8wNfDjtQgrG2H1L7FwHXxbic", "chain": "solana", "arkhamEntity": {"name": "BonkSwap", "note": "", "id": "bonkswap", "type": "dex", "service": null, "addresses": null, "website": "https://www.bonkswap.io/", "twitter": "https://x.com/bonkswap_io"}, "isUserAddress": false, "ownerAddress": {"address": "8NyaPDJeC2eaBGpkRpZKnD9S448AZGgjSvumFe92DRK2", "chain": "solana", "arkhamEntity": {"name": "BonkSwap", "note": "", "id": "bonkswap", "type": "dex", "service": null, "addresses": null, "website": "https://www.bonkswap.io/", "twitter": "https://x.com/bonkswap_io"}, "arkhamLabel": {"name": "Vault Authority", "address": "8NyaPDJeC2eaBGpkRpZKnD9S448AZGgjSvumFe92DRK2", "chainType": "solana"}, "isUserAddress": false, "service": false, "program": false}}, "usd": 390.61061251508, "transactionCount": 22, "flow": "all", "chains": ["solana"]}, {"address": {"address": "6KCGRKoyiUEbF8J6TbrKn3w9Zk6uygZwwAN6yy7brNzj", "chain": "solana", "isUserAddress": false, "ownerAddress": {"address": "7Hvu5R6gN1ut4L5qW2PPexgteEAQH3wUwJdQvTjwpJq", "chain": "solana", "isUserAddress": false, "program": false}}, "usd": 388.7051239013672, "transactionCount": 2, "flow": "all", "chains": ["solana"]}, {"address": {"address": "GdRr8u8c5deY6Sn22DLoCY6wNteb3vNTRUrJjbpf7dQf", "chain": "solana", "arkhamEntity": {"name": "Meteora (Prev. Mercurial)", "note": "", "id": "meteora", "type": "dex", "service": null, "addresses": null, "website": "https://www.meteora.ag", "twitter": "https://x.com/MeteoraAG"}, "arkhamLabel": {"name": "Pool", "address": "GdRr8u8c5deY6Sn22DLoCY6wNteb3vNTRUrJjbpf7dQf", "chainType": "solana"}, "isUserAddress": false, "ownerAddress": {"address": "31p1hptjhFo6ZD8oBqkfutNXQKGGPyi7YcEAfsyKW777", "chain": "solana", "arkhamEntity": {"name": "Meteora (Prev. Mercurial)", "note": "", "id": "meteora", "type": "dex", "service": null, "addresses": null, "website": "https://www.meteora.ag", "twitter": "https://x.com/MeteoraAG"}, "arkhamLabel": {"name": "Market", "address": "31p1hptjhFo6ZD8oBqkfutNXQKGGPyi7YcEAfsyKW777", "chainType": "solana"}, "isUserAddress": false, "service": false, "program": false}}, "usd": 371.30464745440986, "transactionCount": 14, "flow": "all", "chains": ["solana"]}, {"address": {"address": "6LcwQdD9X4cyK82Fhoh6Bdy31NHW2SroYAiGDt5zMij3", "chain": "solana", "isUserAddress": false, "ownerAddress": {"address": "7mJTeHzgkqiRS2TGEmp2FyYMqw468nuEZH2nBHurtDcU", "chain": "solana", "isUserAddress": false, "program": false}}, "usd": 353.3114929199219, "transactionCount": 1, "flow": "in", "chains": ["solana"]}, {"address": {"address": "EDhGw6GM5WFKg3x76x35cLFkdTQ7pyZb6e1fprqiokas", "chain": "solana", "isUserAddress": false, "ownerAddress": {"address": "C1HPDSAmpEsrpwDtobbHZGjJUi7svHadASKh1rFZxekE", "chain": "solana", "isUserAddress": false, "program": false}}, "usd": 339.8401794433594, "transactionCount": 1, "flow": "in", "chains": ["solana"]}, {"address": {"address": "9MSyH6ptUM1a885FUhawyYLd6YfVjDRUhqib4Apqjm3Z", "chain": "solana", "arkhamEntity": {"name": "Orca", "note": "", "id": "orca", "type": "dex", "service": null, "addresses": null, "website": "https://www.orca.so", "twitter": "https://x.com/orca_so"}, "arkhamLabel": {"name": "Pool", "address": "9MSyH6ptUM1a885FUhawyYLd6YfVjDRUhqib4Apqjm3Z", "chainType": "solana"}, "isUserAddress": false, "ownerAddress": {"address": "3ne4mWqdYuNiYrYZC9TrA3FcfuFdErghH97vNPbjicr1", "chain": "solana", "arkhamEntity": {"name": "Orca", "note": "", "id": "orca", "type": "dex", "service": null, "addresses": null, "website": "https://www.orca.so", "twitter": "https://x.com/orca_so"}, "arkhamLabel": {"name": "Market", "address": "3ne4mWqdYuNiYrYZC9TrA3FcfuFdErghH97vNPbjicr1", "chainType": "solana"}, "isUserAddress": false, "service": false, "program": false}}, "usd": 283.28541707992554, "transactionCount": 24, "flow": "all", "chains": ["solana"]}, {"address": {"address": "3kWimcxk1FWKcJ1AmfveJbXGHPaaLnLGQ4eP4RDs7wck", "chain": "solana", "isUserAddress": false, "ownerAddress": {"address": "CirporCojDAnSevGxZPGgRBWUiaD6yvtcg6PCBNpEM6e", "chain": "solana", "isUserAddress": false, "program": false}}, "usd": 274.3414001464844, "transactionCount": 1, "flow": "in", "chains": ["solana"]}, {"address": {"address": "HNSArr3CBDbS5dfUJ7HB6cv7jUAjRsJeDdmtEKAjxgmS", "chain": "solana", "isUserAddress": false, "ownerAddress": {"address": "6kzFfLygRHmNoVZ6HWpQELFbAv7rCkNPMnayyAAsXCby", "chain": "solana", "arkhamLabel": {"name": "\"wahii\" on Pump.fun", "address": "6kzFfLygRHmNoVZ6HWpQELFbAv7rCkNPMnayyAAsXCby", "chainType": "solana"}, "isUserAddress": false, "service": false, "program": false}}, "usd": 247.59548950195312, "transactionCount": 1, "flow": "out", "chains": ["solana"]}, {"address": {"address": "4N8XmVDtARyZZbWwCfU4H92JbWFyyw4aAXj7V1YR5G3S", "chain": "solana", "isUserAddress": false, "ownerAddress": {"address": "CUEUJFnnEvumj1a3fdoawgE4aAfABoArMqyeqpb4P3eN", "chain": "solana", "arkhamLabel": {"name": "trev0r.sol", "address": "CUEUJFnnEvumj1a3fdoawgE4aAfABoArMqyeqpb4P3eN", "chainType": "solana"}, "isUserAddress": false, "service": false, "program": false}}, "usd": 243.36937645077705, "transactionCount": 2, "flow": "in", "chains": ["solana"]}, {"address": {"address": "HF1iQRbC6ptQX5LTJZTrDfone3Yxq6wPXmhQkkVYAHUE", "chain": "solana", "isUserAddress": false, "ownerAddress": {"address": "BUWBvQLa8PY6SwUqE7kEYF3s1Lwq3pNjyxEVv4S7vuhb", "chain": "solana", "isUserAddress": false, "program": false}}, "usd": 216.6830024421215, "transactionCount": 4, "flow": "in", "chains": ["solana"]}, {"address": {"address": "CSRAwFTK8qNJ2xswjGLfgxXPfB3tDc6a3aRVWbe86HEB", "chain": "solana", "isUserAddress": false, "ownerAddress": {"address": "ASVLogbtZzoLLfuGqvZnvpPwsSFmZK8bcMcgbTfFxWLU", "chain": "solana", "isUserAddress": false, "program": false}}, "usd": 197.55242919921875, "transactionCount": 2, "flow": "out", "chains": ["solana"]}, {"address": {"address": "DugwxEmZkNzAH3VfMf8ySCZCGimmkUHG2nxkRmB66sUU", "chain": "solana", "arkhamEntity": {"name": "BonkSwap", "note": "", "id": "bonkswap", "type": "dex", "service": null, "addresses": null, "website": "https://www.bonkswap.io/", "twitter": "https://x.com/bonkswap_io"}, "arkhamLabel": {"name": "Pool", "address": "DugwxEmZkNzAH3VfMf8ySCZCGimmkUHG2nxkRmB66sUU", "chainType": "solana"}, "isUserAddress": false, "ownerAddress": {"address": "8NyaPDJeC2eaBGpkRpZKnD9S448AZGgjSvumFe92DRK2", "chain": "solana", "arkhamEntity": {"name": "BonkSwap", "note": "", "id": "bonkswap", "type": "dex", "service": null, "addresses": null, "website": "https://www.bonkswap.io/", "twitter": "https://x.com/bonkswap_io"}, "arkhamLabel": {"name": "Vault Authority", "address": "8NyaPDJeC2eaBGpkRpZKnD9S448AZGgjSvumFe92DRK2", "chainType": "solana"}, "isUserAddress": false, "service": false, "program": false}}, "usd": 181.94625759124756, "transactionCount": 4, "flow": "out", "chains": ["solana"]}, {"address": {"address": "HWLudMqVVVYbJe6Jebhe1xtm4aZqcfMCBSu6veeAh4ar", "chain": "solana", "isUserAddress": false, "ownerAddress": {"address": "6SY9HQDeQ39L6UTkT9rAhMNkbJEcF8Smurok8GaAFZqA", "chain": "solana", "isUserAddress": false, "program": false}}, "usd": 175.7666473388672, "transactionCount": 1, "flow": "out", "chains": ["solana"]}, {"address": {"address": "CNvcsYfeAFuAc5C9GRQcodTvEB6qBL426WsqpWUzNWBY", "chain": "solana", "isUserAddress": false, "ownerAddress": {"address": "7CUaMvvbe1dWgfLopjRa1XLtemzi5VoPtfdsKdTdiA3p", "chain": "solana", "arkhamLabel": {"name": "\"7CUaMv\" on Pump.fun", "address": "7CUaMvvbe1dWgfLopjRa1XLtemzi5VoPtfdsKdTdiA3p", "chainType": "solana"}, "isUserAddress": false, "service": false, "program": false}}, "usd": 133.35397338867188, "transactionCount": 1, "flow": "out", "chains": ["solana"]}, {"address": {"address": "AYzkndFryWvgu2baaUxb4NRLxh1GLkLdjKzGzEYMsYMH", "chain": "solana", "isUserAddress": false, "ownerAddress": {"address": "HuF1WApwyPEPnveKvFA2aXXiRvLYAvqtRXMK4z7uwYGN", "chain": "solana", "isUserAddress": false, "program": false}}, "usd": 129.59764099121094, "transactionCount": 1, "flow": "out", "chains": ["solana"]}, {"address": {"address": "HJquL2K9fZhuTJkcZJqFsPuThLeNztfpPLbxqaBPci6a", "chain": "solana", "isUserAddress": false, "ownerAddress": {"address": "BSna7DM9X5ZiHwV1szVuo9imZ4odX8KS7GX1w5jBS1DQ", "chain": "solana", "arkhamLabel": {"name": "8nxnznd21updmbsqz7z6xemcy5jntcec3tjzlzviypcg.sol", "address": "BSna7DM9X5ZiHwV1szVuo9imZ4odX8KS7GX1w5jBS1DQ", "chainType": "solana"}, "isUserAddress": false, "service": false, "program": false}}, "usd": 128.72418212890625, "transactionCount": 1, "flow": "out", "chains": ["solana"]}, {"address": {"address": "2u29iRiY88GYevRSwp3jg9dVh3tvoQkMYtXYbSYcc26y", "chain": "solana", "isUserAddress": false, "ownerAddress": {"address": "FbAshUYwUKo1z4KJHfGBQNhMVVBR5CGY6yrFJGMxaZJz", "chain": "solana", "isUserAddress": false, "program": false}}, "usd": 125.88246154785156, "transactionCount": 1, "flow": "in", "chains": ["solana"]}, {"address": {"address": "9m4g6AnamSa32jHa5Far3Xz5hUoFb71PfP7bY4oYxxDa", "chain": "solana", "isUserAddress": false, "ownerAddress": {"address": "4yW2APuorDy5LzpMBGWxcRnx9ttckXfJVh4x4snWynFR", "chain": "solana", "isUserAddress": false, "program": false}}, "usd": 122.8352279663086, "transactionCount": 1, "flow": "out", "chains": ["solana"]}, {"address": {"address": "7DpQAnULQ8ohHZ8Etd6Y9GJyxSmki8nwYne7jjnrkTtS", "chain": "solana", "isUserAddress": false, "ownerAddress": {"address": "7QNYab5cFtQ73e3CyB7JaAGNRWzNLqCSpzVfEgfc3sH5", "chain": "solana", "isUserAddress": false, "program": false}}, "usd": 120.74537658691406, "transactionCount": 1, "flow": "in", "chains": ["solana"]}, {"address": {"address": "66i1ucUah4Qi1sv4KhdonGRsGGr7zmGPeMC3eSzR8Bix", "chain": "solana", "arkhamEntity": {"name": "Meteora (Prev. Mercurial)", "note": "", "id": "meteora", "type": "dex", "service": null, "addresses": null, "website": "https://www.meteora.ag", "twitter": "https://x.com/MeteoraAG"}, "arkhamLabel": {"name": "Vault", "address": "66i1ucUah4Qi1sv4KhdonGRsGGr7zmGPeMC3eSzR8Bix", "chainType": "solana"}, "isUserAddress": false, "ownerAddress": {"address": "J9K67PxqqvCRW9tiDHB9bAisgNQSMLU1bvExtexyd7Ve", "chain": "solana", "arkhamEntity": {"name": "Meteora (Prev. Mercurial)", "note": "", "id": "meteora", "type": "dex", "service": null, "addresses": null, "website": "https://www.meteora.ag", "twitter": "https://x.com/MeteoraAG"}, "arkhamLabel": {"name": "Vault Authority", "address": "J9K67PxqqvCRW9tiDHB9bAisgNQSMLU1bvExtexyd7Ve", "chainType": "solana"}, "isUserAddress": false, "service": false, "program": false}}, "usd": 104.04500078782439, "transactionCount": 38, "flow": "all", "chains": ["solana"]}, {"address": {"address": "77MR2zLM2BQNbZhQDMx82SgRcx2vQumfMQLLfPrSio8k", "chain": "solana", "arkhamEntity": {"name": "Meteora (Prev. Mercurial)", "note": "", "id": "meteora", "type": "dex", "service": null, "addresses": null, "website": "https://www.meteora.ag", "twitter": "https://x.com/MeteoraAG"}, "arkhamLabel": {"name": "Pool", "address": "77MR2zLM2BQNbZhQDMx82SgRcx2vQumfMQLLfPrSio8k", "chainType": "solana"}, "isUserAddress": false, "ownerAddress": {"address": "7eexH14UjhNxJe6zTT3f1Vb1E8iACsBMVaWheDEmxdT2", "chain": "solana", "arkhamEntity": {"name": "Meteora (Prev. Mercurial)", "note": "", "id": "meteora", "type": "dex", "service": null, "addresses": null, "website": "https://www.meteora.ag", "twitter": "https://x.com/MeteoraAG"}, "arkhamLabel": {"name": "Market", "address": "7eexH14UjhNxJe6zTT3f1Vb1E8iACsBMVaWheDEmxdT2", "chainType": "solana"}, "isUserAddress": false, "service": false, "program": false}}, "usd": 97.1608249717392, "transactionCount": 12, "flow": "all", "chains": ["solana"]}, {"address": {"address": "HeDCw7gMyKsBC4R56Y3nZEw6VNQ1G8Fd9SFzMAzrhDbA", "chain": "solana", "isUserAddress": false, "ownerAddress": {"address": "76FVrnb3ii35omHKtHm665s1QGTm84zvFaxyuadiPP1e", "chain": "solana", "isUserAddress": false, "program": false}}, "usd": 91.20777130126953, "transactionCount": 1, "flow": "out", "chains": ["solana"]}, {"address": {"address": "4JSJjRc8eUmrMvgbgVZcPo77XAaGA1gSd4GYixPAjZFN", "chain": "solana", "isUserAddress": false, "ownerAddress": {"address": "7tqAty9v4KVkQFqsPCX3ka6LQA1un7yvcrPCYU12G8CD", "chain": "solana", "isUserAddress": false, "program": false}}, "usd": 89.85139465332031, "transactionCount": 1, "flow": "out", "chains": ["solana"]}, {"address": {"address": "Ci4Xh3SRZ4uqZJULKFha3xWH2A31F7T6MNMnumFLeQMf", "chain": "solana", "arkhamEntity": {"name": "Orca", "note": "", "id": "orca", "type": "dex", "service": null, "addresses": null, "website": "https://www.orca.so", "twitter": "https://x.com/orca_so"}, "arkhamLabel": {"name": "Pool", "address": "Ci4Xh3SRZ4uqZJULKFha3xWH2A31F7T6MNMnumFLeQMf", "chainType": "solana"}, "isUserAddress": false, "ownerAddress": {"address": "8QaXeHBrShJTdtN1rWCccBxpSVvKksQ2PCu5nufb2zbk", "chain": "solana", "arkhamEntity": {"name": "Orca", "note": "", "id": "orca", "type": "dex", "service": null, "addresses": null, "website": "https://www.orca.so", "twitter": "https://x.com/orca_so"}, "arkhamLabel": {"name": "Market", "address": "8QaXeHBrShJTdtN1rWCccBxpSVvKksQ2PCu5nufb2zbk", "chainType": "solana"}, "isUserAddress": false, "service": false, "program": false}}, "usd": 81.2056337594986, "transactionCount": 2, "flow": "in", "chains": ["solana"]}, {"address": {"address": "EHcHNHVctVhc8Rtex1vrjC6JrwaAi3pJyGyEVBuTKS53", "chain": "solana", "isUserAddress": false, "ownerAddress": {"address": "4Jj2DtFMGrHmYyscfVYK8mR9gBcHRAtc2vBjVfPJ9jf5", "chain": "solana", "isUserAddress": false, "program": false}}, "usd": 78.24024200439453, "transactionCount": 1, "flow": "in", "chains": ["solana"]}]}