{"solana": [{"address": {"address": "3vmfn3EHsmAaEXpuN6NxfitMnJFCsrUD3NBvXwKjZzjw", "chain": "solana", "arkhamEntity": {"name": "ZeroFi", "note": "", "id": "zerofi", "type": "dex", "service": null, "addresses": null}, "arkhamLabel": {"name": "Vault", "address": "3vmfn3EHsmAaEXpuN6NxfitMnJFCsrUD3NBvXwKjZzjw", "chainType": "solana"}, "isUserAddress": false, "ownerAddress": {"address": "3vmfn3EHsmAaEXpuN6NxfitMnJFCsrUD3NBvXwKjZzjw", "chain": "solana", "arkhamEntity": {"name": "ZeroFi", "note": "", "id": "zerofi", "type": "dex", "service": null, "addresses": null}, "arkhamLabel": {"name": "Vault", "address": "3vmfn3EHsmAaEXpuN6NxfitMnJFCsrUD3NBvXwKjZzjw", "chainType": "solana"}, "isUserAddress": false, "service": false, "program": false}}, "usd": 17546.829423845746, "transactionCount": 162, "flow": "all", "chains": ["solana"]}, {"address": {"address": "HLo5Yd9fF17XEmFfqK6Ptv4TrgvHHu26aVhouY2FYbKf", "chain": "solana", "isUserAddress": false, "ownerAddress": {"address": "8dS4fdXf3DyiSC33nUNDqtDfugWWRx2gGtPYNZ1V8iQg", "chain": "solana", "isUserAddress": false, "program": false}}, "usd": 15496.33837890625, "transactionCount": 12, "flow": "all", "chains": ["solana"]}, {"address": {"address": "7UYZ4vX13mmGiopayLZAduo8aie77yZ3o8FMzTeAX8uJ", "chain": "solana", "arkhamEntity": {"name": "Raydium", "note": "", "id": "raydium", "type": "dex", "service": null, "addresses": null, "website": "https://raydium.io", "twitter": "https://twitter.com/RaydiumProtocol"}, "isUserAddress": false, "ownerAddress": {"address": "5Q544fKrFoe6tsEbD7S8EmxGTJYAKtTVhAW5Q5pge4j1", "chain": "solana", "arkhamEntity": {"name": "Raydium", "note": "", "id": "raydium", "type": "dex", "service": null, "addresses": null, "website": "https://raydium.io", "twitter": "https://twitter.com/RaydiumProtocol"}, "arkhamLabel": {"name": "Authority V4", "address": "5Q544fKrFoe6tsEbD7S8EmxGTJYAKtTVhAW5Q5pge4j1", "chainType": "solana"}, "isUserAddress": false, "service": false, "program": false}}, "usd": 4828.684920310974, "transactionCount": 8, "flow": "all", "chains": ["solana"]}, {"address": {"address": "VgwuBBGNCVyT3fnEvRPFhMcYsDN9BH66F6nMQoX9azw", "chain": "solana", "arkhamEntity": {"name": "Orca", "note": "", "id": "orca", "type": "dex", "service": null, "addresses": null, "website": "https://www.orca.so", "twitter": "https://x.com/orca_so"}, "arkhamLabel": {"name": "Pool", "address": "VgwuBBGNCVyT3fnEvRPFhMcYsDN9BH66F6nMQoX9azw", "chainType": "solana"}, "isUserAddress": false, "ownerAddress": {"address": "D6NdKrKNQPmRZCCnG1GqXtF7MMoHB7qR6GU5TkG59Qz1", "chain": "solana", "arkhamEntity": {"name": "Orca", "note": "", "id": "orca", "type": "dex", "service": null, "addresses": null, "website": "https://www.orca.so", "twitter": "https://x.com/orca_so"}, "arkhamLabel": {"name": "Market", "address": "D6NdKrKNQPmRZCCnG1GqXtF7MMoHB7qR6GU5TkG59Qz1", "chainType": "solana"}, "isUserAddress": false, "service": false, "program": false}}, "usd": 4032.006306093186, "transactionCount": 120, "flow": "all", "chains": ["solana"]}, {"address": {"address": "4NAjByzibRKtPuK49WHqV6ZyQtQ4hgjzUtouLDphG5eK", "chain": "solana", "isUserAddress": false, "ownerAddress": {"address": "C6Xi6z71oVspEHF4ZYMBckmUPTJpZTvWnTXbYhY1a6Kw", "chain": "solana", "isUserAddress": false, "program": false}}, "usd": 4024.7601113319397, "transactionCount": 2, "flow": "in", "chains": ["solana"]}, {"address": {"address": "6AKBySNVUyGHsAYHxEpzHsaWnEsf5JZTkGnt3k4zBMhE", "chain": "solana", "arkhamEntity": {"name": "Phoenix", "note": "", "id": "phoenix-trade", "type": "dex", "service": null, "addresses": null, "website": "https://www.phoenix.trade", "twitter": "https://x.com/PhoenixTrade"}, "arkhamLabel": {"name": "Pool", "address": "6AKBySNVUyGHsAYHxEpzHsaWnEsf5JZTkGnt3k4zBMhE", "chainType": "solana"}, "userLabel": {"name": "phoenix trade WIF pool", "address": "6AKBySNVUyGHsAYHxEpzHsaWnEsf5JZTkGnt3k4zBMhE", "chainType": "solana"}, "isUserAddress": false, "ownerAddress": {"address": "6AKBySNVUyGHsAYHxEpzHsaWnEsf5JZTkGnt3k4zBMhE", "chain": "solana", "arkhamEntity": {"name": "Phoenix", "note": "", "id": "phoenix-trade", "type": "dex", "service": null, "addresses": null, "website": "https://www.phoenix.trade", "twitter": "https://x.com/PhoenixTrade"}, "arkhamLabel": {"name": "Pool", "address": "6AKBySNVUyGHsAYHxEpzHsaWnEsf5JZTkGnt3k4zBMhE", "chainType": "solana"}, "isUserAddress": false, "service": false, "program": false}}, "usd": 3649.061522603035, "transactionCount": 13, "flow": "all", "chains": ["solana"]}, {"address": {"address": "netFfTV6tNWCRP8dKmTmoWexGVorfLi6Hot4D47ep2w", "chain": "solana", "isUserAddress": false, "ownerAddress": {"address": "7EYixVyNfxyfVgBgtXHoDAQVvG5KhAmT2eADG1nZBUwf", "chain": "solana", "isUserAddress": false, "program": false}}, "usd": 1234.2149658203125, "transactionCount": 1, "flow": "in", "chains": ["solana"]}, {"address": {"address": "BgtsrUyBP8kp6ByNE9yv74DMUtdxPkumhmqH9ZrCCxMA", "chain": "solana", "isUserAddress": false, "ownerAddress": {"address": "7FRehNtm6gXYkDQvMnKftmUWMKxrRjoVQzdRn95Fpy6z", "chain": "solana", "arkhamLabel": {"name": "\"ikaruz\" on Pump.fun", "address": "7FRehNtm6gXYkDQvMnKftmUWMKxrRjoVQzdRn95Fpy6z", "chainType": "solana"}, "isUserAddress": false, "service": false, "program": false}}, "usd": 1010.7694091796875, "transactionCount": 1, "flow": "out", "chains": ["solana"]}, {"address": {"address": "E8JDxN45SMoDopeihZzTFVKkCEQmRvwet2snK688Kn1r", "chain": "solana", "isUserAddress": false, "ownerAddress": {"address": "FJMh9Ne3wyQhVpE2S8zadCQwdAkXSTbrvQzMW9uLnZbC", "chain": "solana", "isUserAddress": false, "program": false}}, "usd": 998.0548706054688, "transactionCount": 1, "flow": "out", "chains": ["solana"]}, {"address": {"address": "FxFJvbmM4BSoagE7JgSHH6d7Myz6GGX4oWb4CCNJ46UD", "chain": "solana", "isUserAddress": false, "ownerAddress": {"address": "4vj38EjA6H9f33A3M88vmRwc7t3ojx4cq8rARhYRZvWn", "chain": "solana", "arkhamLabel": {"name": "hatersgonnahate.sol", "address": "4vj38EjA6H9f33A3M88vmRwc7t3ojx4cq8rARhYRZvWn", "chainType": "solana"}, "isUserAddress": false, "service": false, "program": false}}, "usd": 806.5599779486656, "transactionCount": 2, "flow": "in", "chains": ["solana"]}, {"address": {"address": "G9QhqhVVPMLWV3B1ztAXGJKww8CKYnThS1oPughijjQd", "chain": "solana", "isUserAddress": false, "ownerAddress": {"address": "EnRef4rmKTPTj4179YmHkmxZbUinZqGdywUXisKx8Mw1", "chain": "solana", "isUserAddress": false, "program": false}}, "usd": 574.560546875, "transactionCount": 1, "flow": "in", "chains": ["solana"]}, {"address": {"address": "7Uu3zqymp24n292d3pMF8xyqjHd9tnhYWiHLxW6xCWZG", "chain": "solana", "isUserAddress": false, "ownerAddress": {"address": "NGGuqtsTEKdkNwYMb9i4oWVQ97bMNxB7Gecb7eL4BZF", "chain": "solana", "isUserAddress": false, "program": false}}, "usd": 520.383544921875, "transactionCount": 1, "flow": "out", "chains": ["solana"]}, {"address": {"address": "8wbbDZRuhdrabLpTphDW37Xuw3jgp3uKBPwqh1SZnC6U", "chain": "solana", "isUserAddress": false, "ownerAddress": {"address": "8a4jnTAVc2pmNWHwdvWdwSrusAdkVvGRUk6KV2LpoM9s", "chain": "solana", "isUserAddress": false, "program": false}}, "usd": 497.37518310546875, "transactionCount": 1, "flow": "out", "chains": ["solana"]}, {"address": {"address": "3a9DXq2KdAyB2V2GwaMnNFaJosGAbhiccG9uNohAQJDN", "chain": "solana", "isUserAddress": false, "ownerAddress": {"address": "Bvp1uKAqHL8bds7LQJDY6dkumsyG2WkVgAftCKFmvGYK", "chain": "solana", "isUserAddress": false, "program": false}}, "usd": 207.87449645996094, "transactionCount": 1, "flow": "in", "chains": ["solana"]}, {"address": {"address": "npvYYoaPiX4h6expUv3vqUgdKFfgZPgH9DJqqHNw8V4", "chain": "solana", "arkhamEntity": {"name": "PancakeSwap", "note": "", "id": "pancakeswap", "type": "dex", "service": null, "addresses": null, "website": "https://pancakeswap.finance/", "twitter": "https://twitter.com/PancakeSwap"}, "arkhamLabel": {"name": "Pool", "address": "npvYYoaPiX4h6expUv3vqUgdKFfgZPgH9DJqqHNw8V4", "chainType": "solana"}, "isUserAddress": false, "ownerAddress": {"address": "5HcYQw47hqjxK5u5kqo9nVL6jFYgaKAyU7NtmaJNNXkG", "chain": "solana", "arkhamEntity": {"name": "PancakeSwap", "note": "", "id": "pancakeswap", "type": "dex", "service": null, "addresses": null, "website": "https://pancakeswap.finance/", "twitter": "https://twitter.com/PancakeSwap"}, "arkhamLabel": {"name": "Market", "address": "5HcYQw47hqjxK5u5kqo9nVL6jFYgaKAyU7NtmaJNNXkG", "chainType": "solana"}, "isUserAddress": false, "service": false, "program": false}}, "usd": 158.58301583025604, "transactionCount": 72, "flow": "all", "chains": ["solana"]}, {"address": {"address": "CYEdiigmAEBgfh5ZmaWKXshuGwFeHiBqwVq2Lr8zszae", "chain": "solana", "isUserAddress": false, "ownerAddress": {"address": "AjDonYX7FSKsRUgm7f9aBcsCV6UF4e9cBK5KQq1LfK5i", "chain": "solana", "isUserAddress": false, "program": false}}, "usd": 143.42037963867188, "transactionCount": 1, "flow": "in", "chains": ["solana"]}, {"address": {"address": "BurFp2tGf7wjWJ9UW9miCVxyfLX5eZe6LQwqMbwbZ7qj", "chain": "solana", "isUserAddress": false, "ownerAddress": {"address": "CESNgTzQ23y6nxCbXo8BzBJWDQGhDygKvj8qD4xa4vqE", "chain": "solana", "isUserAddress": false, "program": false}}, "usd": 99.25157165527344, "transactionCount": 1, "flow": "out", "chains": ["solana"]}, {"address": {"address": "EZCxUQKM7eTXD4HovFRJfExEene9bwEMk44rP31CxGXP", "chain": "solana", "isUserAddress": false, "ownerAddress": {"address": "GeFWGYLmzJ2JmdAkMZRKXybomwA5hG2JLRUsbBDioxn9", "chain": "solana", "isUserAddress": false, "program": false}}, "usd": 86.73729705810547, "transactionCount": 1, "flow": "in", "chains": ["solana"]}, {"address": {"address": "Dx4uW2FiJjKtwf4kVTsbMDpVwtnZadZsYFDHWFQzBjTZ", "chain": "solana", "isUserAddress": false, "ownerAddress": {"address": "6Hsro3a2W6Xzei6FvX9k3prUU5kWVb5erGrseqzLB1QJ", "chain": "solana", "isUserAddress": false, "program": false}}, "usd": 72.1817855834961, "transactionCount": 1, "flow": "out", "chains": ["solana"]}, {"address": {"address": "BsHUiq9mYrqhfqei4KBRA74ashrDCUpKbgNFBs3M7WGJ", "chain": "solana", "isUserAddress": false, "ownerAddress": {"address": "8UA5eRPjosVEEVpoSC1wD84RQUynnZL9QVvAB5UX92Cp", "chain": "solana", "isUserAddress": false, "program": false}}, "usd": 68.71572035551071, "transactionCount": 2, "flow": "in", "chains": ["solana"]}, {"address": {"address": "3gyFpeKo15NdgeFiknziZKUGPTVkNNeoNyXEdCHv3bev", "chain": "solana", "isUserAddress": false, "ownerAddress": {"address": "21gtWxkJ1YvAgLUZ4kpNpJEdoQPU9rUPM4e3EyfZdxV2", "chain": "solana", "isUserAddress": false, "program": false}}, "usd": 61.14480209350586, "transactionCount": 1, "flow": "out", "chains": ["solana"]}, {"address": {"address": "4GXFbfupsJJ8aMcE6LNJtZmp9uWYVCn8hx9gcGY5HiJd", "chain": "solana", "arkhamEntity": {"name": "Orca", "note": "", "id": "orca", "type": "dex", "service": null, "addresses": null, "website": "https://www.orca.so", "twitter": "https://x.com/orca_so"}, "arkhamLabel": {"name": "Pool", "address": "4GXFbfupsJJ8aMcE6LNJtZmp9uWYVCn8hx9gcGY5HiJd", "chainType": "solana"}, "isUserAddress": false, "ownerAddress": {"address": "AishPhdJXUHpo3zg2gt5AVfdUg3MPmf8DV8FButvbRJ6", "chain": "solana", "arkhamEntity": {"name": "Orca", "note": "", "id": "orca", "type": "dex", "service": null, "addresses": null, "website": "https://www.orca.so", "twitter": "https://x.com/orca_so"}, "arkhamLabel": {"name": "Market", "address": "AishPhdJXUHpo3zg2gt5AVfdUg3MPmf8DV8FButvbRJ6", "chainType": "solana"}, "isUserAddress": false, "service": false, "program": false}}, "usd": 57.43907006457448, "transactionCount": 21, "flow": "all", "chains": ["solana"]}, {"address": {"address": "J2xEJ9wwYi9bizmezjYzHsNSs2BNaBFxq9Y2uEfDhxmq", "chain": "solana", "arkhamEntity": {"name": "Orca", "note": "", "id": "orca", "type": "dex", "service": null, "addresses": null, "website": "https://www.orca.so", "twitter": "https://x.com/orca_so"}, "arkhamLabel": {"name": "Pool", "address": "J2xEJ9wwYi9bizmezjYzHsNSs2BNaBFxq9Y2uEfDhxmq", "chainType": "solana"}, "isUserAddress": false, "ownerAddress": {"address": "CN8M75cH57DuZNzW5wSUpTXtMrSfXBFScJoQxVCgAXes", "chain": "solana", "arkhamEntity": {"name": "Orca", "note": "", "id": "orca", "type": "dex", "service": null, "addresses": null, "website": "https://www.orca.so", "twitter": "https://x.com/orca_so"}, "arkhamLabel": {"name": "Market", "address": "CN8M75cH57DuZNzW5wSUpTXtMrSfXBFScJoQxVCgAXes", "chainType": "solana"}, "isUserAddress": false, "service": false, "program": false}}, "usd": 50.35642413794994, "transactionCount": 17, "flow": "all", "chains": ["solana"]}, {"address": {"address": "BXcTv8CgBhZNYceaoR1EwMpkxFmfsQPaFLdjCHkmodGf", "chain": "solana", "isUserAddress": false, "ownerAddress": {"address": "8Xj7qGJtbPuyB1z3GzX47FBpqdFW1jDy1G2RbrWSyPZ", "chain": "solana", "isUserAddress": false, "program": false}}, "usd": 45.54540417715907, "transactionCount": 2, "flow": "in", "chains": ["solana"]}, {"address": {"address": "8TGUDLeRyzWyfrXLkAvCadWw5EKJwnPCYNinazav76v3", "chain": "solana", "arkhamEntity": {"name": "Orca", "note": "", "id": "orca", "type": "dex", "service": null, "addresses": null, "website": "https://www.orca.so", "twitter": "https://x.com/orca_so"}, "arkhamLabel": {"name": "Pool", "address": "8TGUDLeRyzWyfrXLkAvCadWw5EKJwnPCYNinazav76v3", "chainType": "solana"}, "isUserAddress": false, "ownerAddress": {"address": "6qgyDW4fHvpTAmfNZvPAuETEbVwRKFVAuuHfNzvEmPkY", "chain": "solana", "arkhamEntity": {"name": "Orca", "note": "", "id": "orca", "type": "dex", "service": null, "addresses": null, "website": "https://www.orca.so", "twitter": "https://x.com/orca_so"}, "arkhamLabel": {"name": "Market", "address": "6qgyDW4fHvpTAmfNZvPAuETEbVwRKFVAuuHfNzvEmPkY", "chainType": "solana"}, "isUserAddress": false, "service": false, "program": false}}, "usd": 41.47138214111328, "transactionCount": 2, "flow": "all", "chains": ["solana"]}, {"address": {"address": "Ah4PAf71M49zZD1g3qZdNUKb8YNJuw9B4jdqB8G4BHth", "chain": "solana", "arkhamEntity": {"name": "Orca", "note": "", "id": "orca", "type": "dex", "service": null, "addresses": null, "website": "https://www.orca.so", "twitter": "https://x.com/orca_so"}, "arkhamLabel": {"name": "Pool", "address": "Ah4PAf71M49zZD1g3qZdNUKb8YNJuw9B4jdqB8G4BHth", "chainType": "solana"}, "isUserAddress": false, "ownerAddress": {"address": "A6cVoMU1Z7oRi9R774QarVxHUmHPQkxQfYVFGNQuAx2b", "chain": "solana", "arkhamEntity": {"name": "Orca", "note": "", "id": "orca", "type": "dex", "service": null, "addresses": null, "website": "https://www.orca.so", "twitter": "https://x.com/orca_so"}, "arkhamLabel": {"name": "Market", "address": "A6cVoMU1Z7oRi9R774QarVxHUmHPQkxQfYVFGNQuAx2b", "chainType": "solana"}, "isUserAddress": false, "service": false, "program": false}}, "usd": 33.38081866502762, "transactionCount": 8, "flow": "all", "chains": ["solana"]}, {"address": {"address": "28u8R3He2Bm9tvWp1BXHuNfzp7mMWyS73agnWJoLs4Ne", "chain": "solana", "arkhamEntity": {"name": "Orca", "note": "", "id": "orca", "type": "dex", "service": null, "addresses": null, "website": "https://www.orca.so", "twitter": "https://x.com/orca_so"}, "arkhamLabel": {"name": "Pool", "address": "28u8R3He2Bm9tvWp1BXHuNfzp7mMWyS73agnWJoLs4Ne", "chainType": "solana"}, "isUserAddress": false, "ownerAddress": {"address": "56Ekyu6uBpTna3LR2qkjHjNbDNkCLWK2Lt3uWh7J2R8Z", "chain": "solana", "arkhamEntity": {"name": "Orca", "note": "", "id": "orca", "type": "dex", "service": null, "addresses": null, "website": "https://www.orca.so", "twitter": "https://x.com/orca_so"}, "arkhamLabel": {"name": "Market", "address": "56Ekyu6uBpTna3LR2qkjHjNbDNkCLWK2Lt3uWh7J2R8Z", "chainType": "solana"}, "isUserAddress": false, "service": false, "program": false}}, "usd": 27.691241331398487, "transactionCount": 15, "flow": "all", "chains": ["solana"]}, {"address": {"address": "9g59Xp3gtZ7rAphmpEJ9ebKMTXm6hQPNpaza1ffQ7cq4", "chain": "solana", "arkhamEntity": {"name": "Orca", "note": "", "id": "orca", "type": "dex", "service": null, "addresses": null, "website": "https://www.orca.so", "twitter": "https://x.com/orca_so"}, "isUserAddress": false, "ownerAddress": {"address": "Fb1TpohXrGNZvg42Smhi1u4cu4XzwCvxQfGeis5dqy6c", "chain": "solana", "arkhamEntity": {"name": "Orca", "note": "", "id": "orca", "type": "dex", "service": null, "addresses": null, "website": "https://www.orca.so", "twitter": "https://x.com/orca_so"}, "isUserAddress": false, "service": false, "program": false}}, "usd": 25.01278718188405, "transactionCount": 13, "flow": "all", "chains": ["solana"]}, {"address": {"address": "DJ4r1Ziz72YVvXzyaXaWqjtGzeUCN8mCHjs4HAjU7n2k", "chain": "solana", "isUserAddress": false, "ownerAddress": {"address": "6jwbCH9GdsCyWftrahgQSL6XpVUKvgC7bhnh9fAemDoc", "chain": "solana", "isUserAddress": false, "program": false}}, "usd": 23.077104568481445, "transactionCount": 1, "flow": "in", "chains": ["solana"]}, {"address": {"address": "7cZF6b5q93cAK59dzoZdaWNt6zTLVEGKZ77drNck1Sas", "chain": "solana", "isUserAddress": false, "ownerAddress": {"address": "HvSEz1oH56XsgAbBsrjFbhb7bKGeM3qQiCjzDQdLo5KQ", "chain": "solana", "isUserAddress": false, "program": false}}, "usd": 16.890938997268677, "transactionCount": 2, "flow": "out", "chains": ["solana"]}, {"address": {"address": "Hbz4Sff9k6WbTFJeQm7zPFzqpSgSW2pRFUZhmqgLgd9c", "chain": "solana", "isUserAddress": false, "ownerAddress": {"address": "4KA8tZn9T93TVdfMNXw2vSdXWHYrnCjFNBaarwKLmrmY", "chain": "solana", "isUserAddress": false, "program": false}}, "usd": 14.731417655944824, "transactionCount": 1, "flow": "in", "chains": ["solana"]}, {"address": {"address": "AYVCD96uUfatBdpRyD2gGeEpMLTBHGoZ1nkHxdYwN8fZ", "chain": "solana", "isUserAddress": false, "ownerAddress": {"address": "5XsUqyWmoVPYLjjfutN66B3biB98BAQAiiS5uHYjPpKR", "chain": "solana", "isUserAddress": false, "program": false}}, "usd": 13.781621932983398, "transactionCount": 1, "flow": "out", "chains": ["solana"]}, {"address": {"address": "5iNs616DGPPxN2o9vs4budo3TyWqFmzrtu47L7qWCmu4", "chain": "solana", "isUserAddress": false, "ownerAddress": {"address": "EvUiPfVbTnRtijPWd7LoU1Dn2BREazL5kKbbW5cc69wg", "chain": "solana", "isUserAddress": false, "program": false}}, "usd": 13.747873306274414, "transactionCount": 1, "flow": "out", "chains": ["solana"]}, {"address": {"address": "SVvsfTZL2sy1tc8PtZFgEisLgCTaJNoMHPa5WFeECoq", "chain": "solana", "arkhamEntity": {"name": "Orca", "note": "", "id": "orca", "type": "dex", "service": null, "addresses": null, "website": "https://www.orca.so", "twitter": "https://x.com/orca_so"}, "arkhamLabel": {"name": "Pool", "address": "SVvsfTZL2sy1tc8PtZFgEisLgCTaJNoMHPa5WFeECoq", "chainType": "solana"}, "isUserAddress": false, "ownerAddress": {"address": "BWB9XA6Gic4iAsaQjX8ssszHLBX8CGurVm4sGWZa2nwb", "chain": "solana", "arkhamEntity": {"name": "Orca", "note": "", "id": "orca", "type": "dex", "service": null, "addresses": null, "website": "https://www.orca.so", "twitter": "https://x.com/orca_so"}, "arkhamLabel": {"name": "Market", "address": "BWB9XA6Gic4iAsaQjX8ssszHLBX8CGurVm4sGWZa2nwb", "chainType": "solana"}, "isUserAddress": false, "service": false, "program": false}}, "usd": 13.30644416809082, "transactionCount": 2, "flow": "all", "chains": ["solana"]}, {"address": {"address": "8J94EoT7G9cBfsHs9bdfjZK7EMxbrEkQjHKx4YZSxXwH", "chain": "solana", "isUserAddress": false, "ownerAddress": {"address": "Hs6jZJi9msA8vFUKEvS6N8HVoqYkZYbv69tNvVhFLXJH", "chain": "solana", "isUserAddress": false, "program": false}}, "usd": 12.682291030883789, "transactionCount": 1, "flow": "out", "chains": ["solana"]}, {"address": {"address": "F3iRpKJ5txvkHwxJVgGY7h3AS3ZJxa9QEJDZkiDzWWgZ", "chain": "solana", "isUserAddress": false, "ownerAddress": {"address": "2cwikLahAmGdtHhS3gUZhJPqEmG1xwkGjuTJNugzhwZU", "chain": "solana", "isUserAddress": false, "program": false}}, "usd": 12.594194412231445, "transactionCount": 1, "flow": "out", "chains": ["solana"]}, {"address": {"address": "4tMFwUiDJfPD9sQ4TCbrGJicX7fb1qBtC45QHwERT9JE", "chain": "solana", "arkhamEntity": {"name": "Meteora (Prev. Mercurial)", "note": "", "id": "meteora", "type": "dex", "service": null, "addresses": null, "website": "https://www.meteora.ag", "twitter": "https://x.com/MeteoraAG"}, "arkhamLabel": {"name": "Vault", "address": "4tMFwUiDJfPD9sQ4TCbrGJicX7fb1qBtC45QHwERT9JE", "chainType": "solana"}, "isUserAddress": false, "ownerAddress": {"address": "Bd4p4YA6DQsF3hdDDGWFiSgQX7dTqJCpwVqiuGvStV7z", "chain": "solana", "arkhamEntity": {"name": "Meteora (Prev. Mercurial)", "note": "", "id": "meteora", "type": "dex", "service": null, "addresses": null, "website": "https://www.meteora.ag", "twitter": "https://x.com/MeteoraAG"}, "arkhamLabel": {"name": "Vault Authority", "address": "Bd4p4YA6DQsF3hdDDGWFiSgQX7dTqJCpwVqiuGvStV7z", "chainType": "solana"}, "isUserAddress": false, "service": false, "program": false}}, "usd": 12.014649659395218, "transactionCount": 10, "flow": "all", "chains": ["solana"]}, {"address": {"address": "23ALMaQ8rANHBqFT9TbVe2X7uGoDJNcR1Dsw7v63c64J", "chain": "solana", "isUserAddress": false, "ownerAddress": {"address": "Frs9ySzi8jqVVUAUtC82HBuJjk3rmdFQ2CJk93eRi3vw", "chain": "solana", "isUserAddress": false, "program": false}}, "usd": 10.571938633918762, "transactionCount": 3, "flow": "all", "chains": ["solana"]}, {"address": {"address": "5aLWG4CxHZZwVQ69uu4Br8oiFyJ5P3NtMkGX9BDm6AVv", "chain": "solana", "arkhamEntity": {"name": "Meteora (Prev. Mercurial)", "note": "", "id": "meteora", "type": "dex", "service": null, "addresses": null, "website": "https://www.meteora.ag", "twitter": "https://x.com/MeteoraAG"}, "arkhamLabel": {"name": "Pool", "address": "5aLWG4CxHZZwVQ69uu4Br8oiFyJ5P3NtMkGX9BDm6AVv", "chainType": "solana"}, "isUserAddress": false, "ownerAddress": {"address": "8WBdqT2pE3P6yDVCFTxknQL3wLRj8g8ZWoNZiXHBUHBL", "chain": "solana", "arkhamEntity": {"name": "Meteora (Prev. Mercurial)", "note": "", "id": "meteora", "type": "dex", "service": null, "addresses": null, "website": "https://www.meteora.ag", "twitter": "https://x.com/MeteoraAG"}, "arkhamLabel": {"name": "Market", "address": "8WBdqT2pE3P6yDVCFTxknQL3wLRj8g8ZWoNZiXHBUHBL", "chainType": "solana"}, "isUserAddress": false, "service": false, "program": false}}, "usd": 8.175377443665639, "transactionCount": 6, "flow": "all", "chains": ["solana"]}, {"address": {"address": "Fb79LDWeGagaEgcdEwVp79HvwJcFQ9ezCrxQCEkywdhL", "chain": "solana", "isUserAddress": false, "ownerAddress": {"address": "BeanzMQ6UzLDesw7oxkJH64FSpoqHMQrz93SGA4UEZZL", "chain": "solana", "isUserAddress": false, "program": false}}, "usd": 7.969130992889404, "transactionCount": 1, "flow": "in", "chains": ["solana"]}, {"address": {"address": "EJcuGkiZ3EbDCikPuWperRDHS4afLPkgz1LF4DpJrLrd", "chain": "solana", "arkhamEntity": {"name": "Orca", "note": "", "id": "orca", "type": "dex", "service": null, "addresses": null, "website": "https://www.orca.so", "twitter": "https://x.com/orca_so"}, "arkhamLabel": {"name": "Pool", "address": "EJcuGkiZ3EbDCikPuWperRDHS4afLPkgz1LF4DpJrLrd", "chainType": "solana"}, "isUserAddress": false, "ownerAddress": {"address": "3gpyRVcdbH6Jy1AR5Xz5hypNGyGWECLXM5eaA79z4GdQ", "chain": "solana", "arkhamEntity": {"name": "Orca", "note": "", "id": "orca", "type": "dex", "service": null, "addresses": null, "website": "https://www.orca.so", "twitter": "https://x.com/orca_so"}, "arkhamLabel": {"name": "Market", "address": "3gpyRVcdbH6Jy1AR5Xz5hypNGyGWECLXM5eaA79z4GdQ", "chainType": "solana"}, "isUserAddress": false, "service": false, "program": false}}, "usd": 7.333399186260067, "transactionCount": 14, "flow": "all", "chains": ["solana"]}, {"address": {"address": "Fx85vox1TMM2ppt5c4gAbrQFct4tEakbbw6DdyVTMAse", "chain": "solana", "isUserAddress": false, "ownerAddress": {"address": "E12eEiENStLGv97noMofPcDUC3oA5J8XNjy4vVFHPG3J", "chain": "solana", "isUserAddress": false, "program": false}}, "usd": 6.591426372528076, "transactionCount": 1, "flow": "out", "chains": ["solana"]}, {"address": {"address": "AN1WYWLgVcQvTmag2mufYwJj1CZAwbWaKZoiKZkqZNWf", "chain": "solana", "isUserAddress": false, "ownerAddress": {"address": "3y4BoxjtW7L94YmxKFXBXqwx4z4sA8yiJAeoz9keewK1", "chain": "solana", "isUserAddress": false, "program": false}}, "usd": 5.995695114135742, "transactionCount": 1, "flow": "in", "chains": ["solana"]}, {"address": {"address": "6HqscrXWBaEUKd3yphHHxoqPcmsZ7GhLaJGynBtJdKX4", "chain": "solana", "isUserAddress": false, "ownerAddress": {"address": "9Q9LdSUdkQq7JgoZFuhnMRWHpgR3YMCkxVbpfLUXeDd8", "chain": "solana", "isUserAddress": false, "program": false}}, "usd": 5.6550774574279785, "transactionCount": 1, "flow": "in", "chains": ["solana"]}, {"address": {"address": "FY5msYDheu4zYQc8d99J3PQrdqa5pSbGFTqphXaaoL8i", "chain": "solana", "arkhamEntity": {"name": "Orca", "note": "", "id": "orca", "type": "dex", "service": null, "addresses": null, "website": "https://www.orca.so", "twitter": "https://x.com/orca_so"}, "arkhamLabel": {"name": "Pool", "address": "FY5msYDheu4zYQc8d99J3PQrdqa5pSbGFTqphXaaoL8i", "chainType": "solana"}, "isUserAddress": false, "ownerAddress": {"address": "CZrvf5cCAf7BoTqLkMEsT2czJobx4zfppHez2gaJwHaF", "chain": "solana", "arkhamEntity": {"name": "Orca", "note": "", "id": "orca", "type": "dex", "service": null, "addresses": null, "website": "https://www.orca.so", "twitter": "https://x.com/orca_so"}, "arkhamLabel": {"name": "Market", "address": "CZrvf5cCAf7BoTqLkMEsT2czJobx4zfppHez2gaJwHaF", "chainType": "solana"}, "isUserAddress": false, "service": false, "program": false}}, "usd": 5.00963389640674, "transactionCount": 24, "flow": "all", "chains": ["solana"]}, {"address": {"address": "7VNCk3g61WgRpBn7Q1g4Uz7z2YHoTY7ZR8QcWY4gAQ8", "chain": "solana", "isUserAddress": false, "ownerAddress": {"address": "CA2y5erS9U995ZbQy42ARcZ7Y8bA3vP7YaiDDsBcQq9D", "chain": "solana", "isUserAddress": false, "program": false}}, "usd": 4.9992096847854555, "transactionCount": 2, "flow": "in", "chains": ["solana"]}, {"address": {"address": "CTJPjPRCBDNbxXt6vnhdt93L9QBbuZpvZch9QJ2NctXK", "chain": "solana", "isUserAddress": false, "ownerAddress": {"address": "F3kfJRhxhxxwPcwkSgeDWxQ5v1sCVgpcnR2rYr9DQdZC", "chain": "solana", "isUserAddress": false, "program": false}}, "usd": 4.987386226654053, "transactionCount": 1, "flow": "out", "chains": ["solana"]}, {"address": {"address": "8ASXifQJiP7oT2vyYVYrZ74NFmMG9eE7qTy6msJcPoto", "chain": "solana", "isUserAddress": false, "ownerAddress": {"address": "2qehUdNNtnwHmt5jyqNMgShq9uWwgMh5JfXA1696TDhJ", "chain": "solana", "isUserAddress": false, "program": false}}, "usd": 4.17818021774292, "transactionCount": 1, "flow": "in", "chains": ["solana"]}, {"address": {"address": "2rtDyrP2Hdvku2QG9Eesw9LEwf2MHLu25f8jkF8pmfkJ", "chain": "solana", "isUserAddress": false, "ownerAddress": {"address": "kqRGqjw5g4n8ArHioCkY5zchcVLFvZuy9oh4iM6WDKH", "chain": "solana", "isUserAddress": false, "program": false}}, "usd": 2.5632684230804443, "transactionCount": 1, "flow": "out", "chains": ["solana"]}, {"address": {"address": "AAyMdmoQmK3TkdhM5GoV9WqSiPkmSSrQQi1c3fr3WHrc", "chain": "solana", "arkhamEntity": {"name": "Meteora (Prev. Mercurial)", "note": "", "id": "meteora", "type": "dex", "service": null, "addresses": null, "website": "https://www.meteora.ag", "twitter": "https://x.com/MeteoraAG"}, "arkhamLabel": {"name": "Pool", "address": "AAyMdmoQmK3TkdhM5GoV9WqSiPkmSSrQQi1c3fr3WHrc", "chainType": "solana"}, "isUserAddress": false, "ownerAddress": {"address": "4qkAKTeoQhPpa2y1SNB1Di9NBuWDUEzrN2n4cUqohZ2d", "chain": "solana", "arkhamEntity": {"name": "Meteora (Prev. Mercurial)", "note": "", "id": "meteora", "type": "dex", "service": null, "addresses": null, "website": "https://www.meteora.ag", "twitter": "https://x.com/MeteoraAG"}, "arkhamLabel": {"name": "Market", "address": "4qkAKTeoQhPpa2y1SNB1Di9NBuWDUEzrN2n4cUqohZ2d", "chainType": "solana"}, "isUserAddress": false, "service": false, "program": false}}, "usd": 1.9864638606086373, "transactionCount": 6, "flow": "out", "chains": ["solana"]}]}