{"solana": [{"address": {"address": "3vmfn3EHsmAaEXpuN6NxfitMnJFCsrUD3NBvXwKjZzjw", "chain": "solana", "arkhamEntity": {"name": "ZeroFi", "note": "", "id": "zerofi", "type": "dex", "service": null, "addresses": null}, "arkhamLabel": {"name": "Vault", "address": "3vmfn3EHsmAaEXpuN6NxfitMnJFCsrUD3NBvXwKjZzjw", "chainType": "solana"}, "isUserAddress": false, "ownerAddress": {"address": "3vmfn3EHsmAaEXpuN6NxfitMnJFCsrUD3NBvXwKjZzjw", "chain": "solana", "arkhamEntity": {"name": "ZeroFi", "note": "", "id": "zerofi", "type": "dex", "service": null, "addresses": null}, "arkhamLabel": {"name": "Vault", "address": "3vmfn3EHsmAaEXpuN6NxfitMnJFCsrUD3NBvXwKjZzjw", "chainType": "solana"}, "isUserAddress": false, "service": false, "program": false}}, "usd": 1995.246371269226, "transactionCount": 75, "flow": "all", "chains": ["solana"]}, {"address": {"address": "VgwuBBGNCVyT3fnEvRPFhMcYsDN9BH66F6nMQoX9azw", "chain": "solana", "arkhamEntity": {"name": "Orca", "note": "", "id": "orca", "type": "dex", "service": null, "addresses": null, "website": "https://www.orca.so", "twitter": "https://x.com/orca_so"}, "arkhamLabel": {"name": "Pool", "address": "VgwuBBGNCVyT3fnEvRPFhMcYsDN9BH66F6nMQoX9azw", "chainType": "solana"}, "isUserAddress": false, "ownerAddress": {"address": "D6NdKrKNQPmRZCCnG1GqXtF7MMoHB7qR6GU5TkG59Qz1", "chain": "solana", "arkhamEntity": {"name": "Orca", "note": "", "id": "orca", "type": "dex", "service": null, "addresses": null, "website": "https://www.orca.so", "twitter": "https://x.com/orca_so"}, "arkhamLabel": {"name": "Market", "address": "D6NdKrKNQPmRZCCnG1GqXtF7MMoHB7qR6GU5TkG59Qz1", "chainType": "solana"}, "isUserAddress": false, "service": false, "program": false}}, "usd": 1816.4314680099487, "transactionCount": 67, "flow": "all", "chains": ["solana"]}, {"address": {"address": "6AKBySNVUyGHsAYHxEpzHsaWnEsf5JZTkGnt3k4zBMhE", "chain": "solana", "arkhamEntity": {"name": "Phoenix", "note": "", "id": "phoenix-trade", "type": "dex", "service": null, "addresses": null, "website": "https://www.phoenix.trade", "twitter": "https://x.com/PhoenixTrade"}, "arkhamLabel": {"name": "Pool", "address": "6AKBySNVUyGHsAYHxEpzHsaWnEsf5JZTkGnt3k4zBMhE", "chainType": "solana"}, "userLabel": {"name": "phoenix trade WIF pool", "address": "6AKBySNVUyGHsAYHxEpzHsaWnEsf5JZTkGnt3k4zBMhE", "chainType": "solana"}, "isUserAddress": false, "ownerAddress": {"address": "6AKBySNVUyGHsAYHxEpzHsaWnEsf5JZTkGnt3k4zBMhE", "chain": "solana", "arkhamEntity": {"name": "Phoenix", "note": "", "id": "phoenix-trade", "type": "dex", "service": null, "addresses": null, "website": "https://www.phoenix.trade", "twitter": "https://x.com/PhoenixTrade"}, "arkhamLabel": {"name": "Pool", "address": "6AKBySNVUyGHsAYHxEpzHsaWnEsf5JZTkGnt3k4zBMhE", "chainType": "solana"}, "isUserAddress": false, "service": false, "program": false}}, "usd": 102.96471977233887, "transactionCount": 5, "flow": "all", "chains": ["solana"]}, {"address": {"address": "7UYZ4vX13mmGiopayLZAduo8aie77yZ3o8FMzTeAX8uJ", "chain": "solana", "arkhamEntity": {"name": "Raydium", "note": "", "id": "raydium", "type": "dex", "service": null, "addresses": null, "website": "https://raydium.io", "twitter": "https://twitter.com/RaydiumProtocol"}, "isUserAddress": false, "ownerAddress": {"address": "5Q544fKrFoe6tsEbD7S8EmxGTJYAKtTVhAW5Q5pge4j1", "chain": "solana", "arkhamEntity": {"name": "Raydium", "note": "", "id": "raydium", "type": "dex", "service": null, "addresses": null, "website": "https://raydium.io", "twitter": "https://twitter.com/RaydiumProtocol"}, "arkhamLabel": {"name": "Authority V4", "address": "5Q544fKrFoe6tsEbD7S8EmxGTJYAKtTVhAW5Q5pge4j1", "chainType": "solana"}, "isUserAddress": false, "service": false, "program": false}}, "usd": 94.66587257385254, "transactionCount": 3, "flow": "all", "chains": ["solana"]}, {"address": {"address": "28u8R3He2Bm9tvWp1BXHuNfzp7mMWyS73agnWJoLs4Ne", "chain": "solana", "arkhamEntity": {"name": "Orca", "note": "", "id": "orca", "type": "dex", "service": null, "addresses": null, "website": "https://www.orca.so", "twitter": "https://x.com/orca_so"}, "arkhamLabel": {"name": "Pool", "address": "28u8R3He2Bm9tvWp1BXHuNfzp7mMWyS73agnWJoLs4Ne", "chainType": "solana"}, "isUserAddress": false, "ownerAddress": {"address": "56Ekyu6uBpTna3LR2qkjHjNbDNkCLWK2Lt3uWh7J2R8Z", "chain": "solana", "arkhamEntity": {"name": "Orca", "note": "", "id": "orca", "type": "dex", "service": null, "addresses": null, "website": "https://www.orca.so", "twitter": "https://x.com/orca_so"}, "arkhamLabel": {"name": "Market", "address": "56Ekyu6uBpTna3LR2qkjHjNbDNkCLWK2Lt3uWh7J2R8Z", "chainType": "solana"}, "isUserAddress": false, "service": false, "program": false}}, "usd": 41.0207462310791, "transactionCount": 3, "flow": "all", "chains": ["solana"]}, {"address": {"address": "8TGUDLeRyzWyfrXLkAvCadWw5EKJwnPCYNinazav76v3", "chain": "solana", "arkhamEntity": {"name": "Orca", "note": "", "id": "orca", "type": "dex", "service": null, "addresses": null, "website": "https://www.orca.so", "twitter": "https://x.com/orca_so"}, "arkhamLabel": {"name": "Pool", "address": "8TGUDLeRyzWyfrXLkAvCadWw5EKJwnPCYNinazav76v3", "chainType": "solana"}, "isUserAddress": false, "ownerAddress": {"address": "6qgyDW4fHvpTAmfNZvPAuETEbVwRKFVAuuHfNzvEmPkY", "chain": "solana", "arkhamEntity": {"name": "Orca", "note": "", "id": "orca", "type": "dex", "service": null, "addresses": null, "website": "https://www.orca.so", "twitter": "https://x.com/orca_so"}, "arkhamLabel": {"name": "Market", "address": "6qgyDW4fHvpTAmfNZvPAuETEbVwRKFVAuuHfNzvEmPkY", "chainType": "solana"}, "isUserAddress": false, "service": false, "program": false}}, "usd": 20.020967483520508, "transactionCount": 1, "flow": "in", "chains": ["solana"]}, {"address": {"address": "5aLWG4CxHZZwVQ69uu4Br8oiFyJ5P3NtMkGX9BDm6AVv", "chain": "solana", "arkhamEntity": {"name": "Meteora (Prev. Mercurial)", "note": "", "id": "meteora", "type": "dex", "service": null, "addresses": null, "website": "https://www.meteora.ag", "twitter": "https://x.com/MeteoraAG"}, "arkhamLabel": {"name": "Pool", "address": "5aLWG4CxHZZwVQ69uu4Br8oiFyJ5P3NtMkGX9BDm6AVv", "chainType": "solana"}, "isUserAddress": false, "ownerAddress": {"address": "8WBdqT2pE3P6yDVCFTxknQL3wLRj8g8ZWoNZiXHBUHBL", "chain": "solana", "arkhamEntity": {"name": "Meteora (Prev. Mercurial)", "note": "", "id": "meteora", "type": "dex", "service": null, "addresses": null, "website": "https://www.meteora.ag", "twitter": "https://x.com/MeteoraAG"}, "arkhamLabel": {"name": "Market", "address": "8WBdqT2pE3P6yDVCFTxknQL3wLRj8g8ZWoNZiXHBUHBL", "chainType": "solana"}, "isUserAddress": false, "service": false, "program": false}}, "usd": 17.375539779663086, "transactionCount": 1, "flow": "out", "chains": ["solana"]}, {"address": {"address": "4GXFbfupsJJ8aMcE6LNJtZmp9uWYVCn8hx9gcGY5HiJd", "chain": "solana", "arkhamEntity": {"name": "Orca", "note": "", "id": "orca", "type": "dex", "service": null, "addresses": null, "website": "https://www.orca.so", "twitter": "https://x.com/orca_so"}, "arkhamLabel": {"name": "Pool", "address": "4GXFbfupsJJ8aMcE6LNJtZmp9uWYVCn8hx9gcGY5HiJd", "chainType": "solana"}, "isUserAddress": false, "ownerAddress": {"address": "AishPhdJXUHpo3zg2gt5AVfdUg3MPmf8DV8FButvbRJ6", "chain": "solana", "arkhamEntity": {"name": "Orca", "note": "", "id": "orca", "type": "dex", "service": null, "addresses": null, "website": "https://www.orca.so", "twitter": "https://x.com/orca_so"}, "arkhamLabel": {"name": "Market", "address": "AishPhdJXUHpo3zg2gt5AVfdUg3MPmf8DV8FButvbRJ6", "chainType": "solana"}, "isUserAddress": false, "service": false, "program": false}}, "usd": 14.072931289672852, "transactionCount": 1, "flow": "in", "chains": ["solana"]}]}