{"solana": [{"address": {"address": "AdEo1Hju6MaRQQvR2hPd2GBndfVZBdmdYwn3komL8fDr", "chain": "solana", "isUserAddress": false, "ownerAddress": {"address": "CzaYfC2EnNTyy1Z3gN1ihiHyYazirFB3zLFbuhVSs6Ko", "chain": "solana", "isUserAddress": false, "program": false}}, "usd": 50534.25, "transactionCount": 1, "flow": "in", "chains": ["solana"]}, {"address": {"address": "7UzQ9MZCNoqFAgCqGNEMb9DuKFQaCv3b77WNdvhMLGbs", "chain": "solana", "arkhamEntity": {"name": "Jupiter", "note": "", "id": "jupiter", "type": "dex-aggregator", "service": null, "addresses": null, "website": "https://jup.ag", "twitter": "https://x.com/JupiterExchange"}, "isUserAddress": false, "ownerAddress": {"address": "JD38n7ynKYcgPpF7k1BhXEeREu1KqptU93fVGy3S624k", "chain": "solana", "arkhamEntity": {"name": "Jupiter", "note": "", "id": "jupiter", "type": "dex-aggregator", "service": null, "addresses": null, "website": "https://jup.ag", "twitter": "https://x.com/JupiterExchange"}, "arkhamLabel": {"name": "DCA", "address": "JD38n7ynKYcgPpF7k1BhXEeREu1KqptU93fVGy3S624k", "chainType": "solana"}, "isUserAddress": false, "service": false, "program": false}}, "usd": 21052.925048828125, "transactionCount": 20, "flow": "out", "chains": ["solana"]}, {"address": {"address": "9X2ZdoTEMoRET5GwXaWxJ8ztJV28Up2ooRj38nv5ADqb", "chain": "solana", "arkhamEntity": {"name": "Jupiter", "note": "", "id": "jupiter", "type": "dex-aggregator", "service": null, "addresses": null, "website": "https://jup.ag", "twitter": "https://x.com/JupiterExchange"}, "isUserAddress": false, "ownerAddress": {"address": "JD25qVdtd65FoiXNmR89JjmoJdYk9sjYQeSTZAALFiMy", "chain": "solana", "arkhamEntity": {"name": "Jupiter", "note": "", "id": "jupiter", "type": "dex-aggregator", "service": null, "addresses": null, "website": "https://jup.ag", "twitter": "https://x.com/JupiterExchange"}, "arkhamLabel": {"name": "DCA", "address": "JD25qVdtd65FoiXNmR89JjmoJdYk9sjYQeSTZAALFiMy", "chainType": "solana"}, "isUserAddress": false, "service": false, "program": false}}, "usd": 15727.512573242188, "transactionCount": 15, "flow": "out", "chains": ["solana"]}, {"address": {"address": "CzaYfC2EnNTyy1Z3gN1ihiHyYazirFB3zLFbuhVSs6Ko", "chain": "solana", "isUserAddress": false}, "usd": 0.26137450337409973, "transactionCount": 1, "flow": "in", "chains": ["solana"]}]}