{"solana": [{"address": {"address": "3vmfn3EHsmAaEXpuN6NxfitMnJFCsrUD3NBvXwKjZzjw", "chain": "solana", "arkhamEntity": {"name": "ZeroFi", "note": "", "id": "zerofi", "type": "dex", "service": null, "addresses": null}, "arkhamLabel": {"name": "Vault", "address": "3vmfn3EHsmAaEXpuN6NxfitMnJFCsrUD3NBvXwKjZzjw", "chainType": "solana"}, "isUserAddress": false, "ownerAddress": {"address": "3vmfn3EHsmAaEXpuN6NxfitMnJFCsrUD3NBvXwKjZzjw", "chain": "solana", "arkhamEntity": {"name": "ZeroFi", "note": "", "id": "zerofi", "type": "dex", "service": null, "addresses": null}, "arkhamLabel": {"name": "Vault", "address": "3vmfn3EHsmAaEXpuN6NxfitMnJFCsrUD3NBvXwKjZzjw", "chainType": "solana"}, "isUserAddress": false, "service": false, "program": false}}, "usd": 1344.569275856018, "transactionCount": 113, "flow": "all", "chains": ["solana"]}, {"address": {"address": "VgwuBBGNCVyT3fnEvRPFhMcYsDN9BH66F6nMQoX9azw", "chain": "solana", "arkhamEntity": {"name": "Orca", "note": "", "id": "orca", "type": "dex", "service": null, "addresses": null, "website": "https://www.orca.so", "twitter": "https://x.com/orca_so"}, "arkhamLabel": {"name": "Pool", "address": "VgwuBBGNCVyT3fnEvRPFhMcYsDN9BH66F6nMQoX9azw", "chainType": "solana"}, "isUserAddress": false, "ownerAddress": {"address": "D6NdKrKNQPmRZCCnG1GqXtF7MMoHB7qR6GU5TkG59Qz1", "chain": "solana", "arkhamEntity": {"name": "Orca", "note": "", "id": "orca", "type": "dex", "service": null, "addresses": null, "website": "https://www.orca.so", "twitter": "https://x.com/orca_so"}, "arkhamLabel": {"name": "Market", "address": "D6NdKrKNQPmRZCCnG1GqXtF7MMoHB7qR6GU5TkG59Qz1", "chainType": "solana"}, "isUserAddress": false, "service": false, "program": false}}, "usd": 1054.515346288681, "transactionCount": 83, "flow": "all", "chains": ["solana"]}, {"address": {"address": "CqQMFUCEMbK9Cp9yMonmthKqzc59Ta48JpZMZsh1bDqf", "chain": "solana", "arkhamEntity": {"name": "Jupiter", "note": "", "id": "jupiter", "type": "dex-aggregator", "service": null, "addresses": null, "website": "https://jup.ag", "twitter": "https://x.com/JupiterExchange"}, "isUserAddress": false, "ownerAddress": {"address": "GGztQqQ6pCPaJQnNpXBgELr5cs3WwDakRbh1iEMzjgSJ", "chain": "solana", "arkhamEntity": {"name": "Jupiter", "note": "", "id": "jupiter", "type": "dex-aggregator", "service": null, "addresses": null, "website": "https://jup.ag", "twitter": "https://x.com/JupiterExchange"}, "arkhamLabel": {"name": "Aggregator Authority", "address": "GGztQqQ6pCPaJQnNpXBgELr5cs3WwDakRbh1iEMzjgSJ", "chainType": "solana"}, "isUserAddress": false, "service": false, "program": false}}, "usd": 193.7838580608368, "transactionCount": 2, "flow": "out", "chains": ["solana"]}, {"address": {"address": "npvYYoaPiX4h6expUv3vqUgdKFfgZPgH9DJqqHNw8V4", "chain": "solana", "arkhamEntity": {"name": "PancakeSwap", "note": "", "id": "pancakeswap", "type": "dex", "service": null, "addresses": null, "website": "https://pancakeswap.finance/", "twitter": "https://twitter.com/PancakeSwap"}, "arkhamLabel": {"name": "Pool", "address": "npvYYoaPiX4h6expUv3vqUgdKFfgZPgH9DJqqHNw8V4", "chainType": "solana"}, "isUserAddress": false, "ownerAddress": {"address": "5HcYQw47hqjxK5u5kqo9nVL6jFYgaKAyU7NtmaJNNXkG", "chain": "solana", "arkhamEntity": {"name": "PancakeSwap", "note": "", "id": "pancakeswap", "type": "dex", "service": null, "addresses": null, "website": "https://pancakeswap.finance/", "twitter": "https://twitter.com/PancakeSwap"}, "arkhamLabel": {"name": "Market", "address": "5HcYQw47hqjxK5u5kqo9nVL6jFYgaKAyU7NtmaJNNXkG", "chainType": "solana"}, "isUserAddress": false, "service": false, "program": false}}, "usd": 96.03505444526672, "transactionCount": 22, "flow": "all", "chains": ["solana"]}, {"address": {"address": "8PbAgMN73p1FMaDLqNyoSPeyh5uUTVFDdK5XanufXSZo", "chain": "solana", "arkhamEntity": {"name": "Jupiter", "note": "", "id": "jupiter", "type": "dex-aggregator", "service": null, "addresses": null, "website": "https://jup.ag", "twitter": "https://x.com/JupiterExchange"}, "isUserAddress": false, "ownerAddress": {"address": "6LXutJvKUw8Q5ue2gCgKHQdAN4suWW8awzFVC6XCguFx", "chain": "solana", "arkhamEntity": {"name": "Jupiter", "note": "", "id": "jupiter", "type": "dex-aggregator", "service": null, "addresses": null, "website": "https://jup.ag", "twitter": "https://x.com/JupiterExchange"}, "arkhamLabel": {"name": "Aggregator Authority", "address": "6LXutJvKUw8Q5ue2gCgKHQdAN4suWW8awzFVC6XCguFx", "chainType": "solana"}, "isUserAddress": false, "service": false, "program": false}}, "usd": 66.39973473548889, "transactionCount": 2, "flow": "in", "chains": ["solana"]}, {"address": {"address": "7uHgqMr7bJMe516zBkd23TnFNoHHdPgesgwLtQNBxCnS", "chain": "solana", "arkhamEntity": {"name": "Jupiter", "note": "", "id": "jupiter", "type": "dex-aggregator", "service": null, "addresses": null, "website": "https://jup.ag", "twitter": "https://x.com/JupiterExchange"}, "isUserAddress": false, "ownerAddress": {"address": "4xDsmeTWPNjgSVSS1VTfzFq3iHZhp77ffPkAmkZkdu71", "chain": "solana", "arkhamEntity": {"name": "Jupiter", "note": "", "id": "jupiter", "type": "dex-aggregator", "service": null, "addresses": null, "website": "https://jup.ag", "twitter": "https://x.com/JupiterExchange"}, "arkhamLabel": {"name": "Aggregator Authority", "address": "4xDsmeTWPNjgSVSS1VTfzFq3iHZhp77ffPkAmkZkdu71", "chainType": "solana"}, "isUserAddress": false, "service": false, "program": false}}, "usd": 63.45712661743164, "transactionCount": 1, "flow": "in", "chains": ["solana"]}, {"address": {"address": "HgSC6VYwwGCUwY8Qg3VvwQNxJ1LMpD8PPtrrkVXugkcP", "chain": "solana", "arkhamEntity": {"name": "Jupiter", "note": "", "id": "jupiter", "type": "dex-aggregator", "service": null, "addresses": null, "website": "https://jup.ag", "twitter": "https://x.com/JupiterExchange"}, "isUserAddress": false, "ownerAddress": {"address": "6U91aKa8pmMxkJwBCfPTmUEfZi6dHe7DcFq2ALvB2tbB", "chain": "solana", "arkhamEntity": {"name": "Jupiter", "note": "", "id": "jupiter", "type": "dex-aggregator", "service": null, "addresses": null, "website": "https://jup.ag", "twitter": "https://x.com/JupiterExchange"}, "arkhamLabel": {"name": "Aggregator Authority", "address": "6U91aKa8pmMxkJwBCfPTmUEfZi6dHe7DcFq2ALvB2tbB", "chainType": "solana"}, "isUserAddress": false, "service": false, "program": false}}, "usd": 63.333457946777344, "transactionCount": 1, "flow": "in", "chains": ["solana"]}, {"address": {"address": "92rbMBEcSyvudgKGbDPqyZUndMXQFmWkMrKi9GJkWqos", "chain": "solana", "arkhamEntity": {"name": "Jupiter", "note": "", "id": "jupiter", "type": "dex-aggregator", "service": null, "addresses": null, "website": "https://jup.ag", "twitter": "https://x.com/JupiterExchange"}, "isUserAddress": false, "ownerAddress": {"address": "BQ72nSv9f3PRyRKCBnHLVrerrv37CYTHm5h3s9VSGQDV", "chain": "solana", "arkhamEntity": {"name": "Jupiter", "note": "", "id": "jupiter", "type": "dex-aggregator", "service": null, "addresses": null, "website": "https://jup.ag", "twitter": "https://x.com/JupiterExchange"}, "arkhamLabel": {"name": "Aggregator Authority", "address": "BQ72nSv9f3PRyRKCBnHLVrerrv37CYTHm5h3s9VSGQDV", "chainType": "solana"}, "isUserAddress": false, "service": false, "program": false}}, "usd": 63.310638427734375, "transactionCount": 1, "flow": "in", "chains": ["solana"]}, {"address": {"address": "D4EwnPB4tYV93Jo1uMQXiaPtjGa3ii97pYfaWY2XktAA", "chain": "solana", "arkhamEntity": {"name": "Jupiter", "note": "", "id": "jupiter", "type": "dex-aggregator", "service": null, "addresses": null, "website": "https://jup.ag", "twitter": "https://x.com/JupiterExchange"}, "isUserAddress": false, "ownerAddress": {"address": "2MFoS3MPtvyQ4Wh4M9pdfPjz6UhVoNbFbGJAskCPCj3h", "chain": "solana", "arkhamEntity": {"name": "Jupiter", "note": "", "id": "jupiter", "type": "dex-aggregator", "service": null, "addresses": null, "website": "https://jup.ag", "twitter": "https://x.com/JupiterExchange"}, "arkhamLabel": {"name": "Aggregator Authority", "address": "2MFoS3MPtvyQ4Wh4M9pdfPjz6UhVoNbFbGJAskCPCj3h", "chainType": "solana"}, "isUserAddress": false, "service": false, "program": false}}, "usd": 62.782569885253906, "transactionCount": 1, "flow": "in", "chains": ["solana"]}, {"address": {"address": "7UYZ4vX13mmGiopayLZAduo8aie77yZ3o8FMzTeAX8uJ", "chain": "solana", "arkhamEntity": {"name": "Raydium", "note": "", "id": "raydium", "type": "dex", "service": null, "addresses": null, "website": "https://raydium.io", "twitter": "https://twitter.com/RaydiumProtocol"}, "isUserAddress": false, "ownerAddress": {"address": "5Q544fKrFoe6tsEbD7S8EmxGTJYAKtTVhAW5Q5pge4j1", "chain": "solana", "arkhamEntity": {"name": "Raydium", "note": "", "id": "raydium", "type": "dex", "service": null, "addresses": null, "website": "https://raydium.io", "twitter": "https://twitter.com/RaydiumProtocol"}, "arkhamLabel": {"name": "Authority V4", "address": "5Q544fKrFoe6tsEbD7S8EmxGTJYAKtTVhAW5Q5pge4j1", "chainType": "solana"}, "isUserAddress": false, "service": false, "program": false}}, "usd": 58.28347969055176, "transactionCount": 2, "flow": "out", "chains": ["solana"]}, {"address": {"address": "J2xEJ9wwYi9bizmezjYzHsNSs2BNaBFxq9Y2uEfDhxmq", "chain": "solana", "arkhamEntity": {"name": "Orca", "note": "", "id": "orca", "type": "dex", "service": null, "addresses": null, "website": "https://www.orca.so", "twitter": "https://x.com/orca_so"}, "arkhamLabel": {"name": "Pool", "address": "J2xEJ9wwYi9bizmezjYzHsNSs2BNaBFxq9Y2uEfDhxmq", "chainType": "solana"}, "isUserAddress": false, "ownerAddress": {"address": "CN8M75cH57DuZNzW5wSUpTXtMrSfXBFScJoQxVCgAXes", "chain": "solana", "arkhamEntity": {"name": "Orca", "note": "", "id": "orca", "type": "dex", "service": null, "addresses": null, "website": "https://www.orca.so", "twitter": "https://x.com/orca_so"}, "arkhamLabel": {"name": "Market", "address": "CN8M75cH57DuZNzW5wSUpTXtMrSfXBFScJoQxVCgAXes", "chainType": "solana"}, "isUserAddress": false, "service": false, "program": false}}, "usd": 35.344825983047485, "transactionCount": 5, "flow": "all", "chains": ["solana"]}, {"address": {"address": "Ah4PAf71M49zZD1g3qZdNUKb8YNJuw9B4jdqB8G4BHth", "chain": "solana", "arkhamEntity": {"name": "Orca", "note": "", "id": "orca", "type": "dex", "service": null, "addresses": null, "website": "https://www.orca.so", "twitter": "https://x.com/orca_so"}, "arkhamLabel": {"name": "Pool", "address": "Ah4PAf71M49zZD1g3qZdNUKb8YNJuw9B4jdqB8G4BHth", "chainType": "solana"}, "isUserAddress": false, "ownerAddress": {"address": "A6cVoMU1Z7oRi9R774QarVxHUmHPQkxQfYVFGNQuAx2b", "chain": "solana", "arkhamEntity": {"name": "Orca", "note": "", "id": "orca", "type": "dex", "service": null, "addresses": null, "website": "https://www.orca.so", "twitter": "https://x.com/orca_so"}, "arkhamLabel": {"name": "Market", "address": "A6cVoMU1Z7oRi9R774QarVxHUmHPQkxQfYVFGNQuAx2b", "chainType": "solana"}, "isUserAddress": false, "service": false, "program": false}}, "usd": 29.643377542495728, "transactionCount": 8, "flow": "all", "chains": ["solana"]}, {"address": {"address": "8TGUDLeRyzWyfrXLkAvCadWw5EKJwnPCYNinazav76v3", "chain": "solana", "arkhamEntity": {"name": "Orca", "note": "", "id": "orca", "type": "dex", "service": null, "addresses": null, "website": "https://www.orca.so", "twitter": "https://x.com/orca_so"}, "arkhamLabel": {"name": "Pool", "address": "8TGUDLeRyzWyfrXLkAvCadWw5EKJwnPCYNinazav76v3", "chainType": "solana"}, "isUserAddress": false, "ownerAddress": {"address": "6qgyDW4fHvpTAmfNZvPAuETEbVwRKFVAuuHfNzvEmPkY", "chain": "solana", "arkhamEntity": {"name": "Orca", "note": "", "id": "orca", "type": "dex", "service": null, "addresses": null, "website": "https://www.orca.so", "twitter": "https://x.com/orca_so"}, "arkhamLabel": {"name": "Market", "address": "6qgyDW4fHvpTAmfNZvPAuETEbVwRKFVAuuHfNzvEmPkY", "chainType": "solana"}, "isUserAddress": false, "service": false, "program": false}}, "usd": 12.888832092285156, "transactionCount": 1, "flow": "in", "chains": ["solana"]}]}