{"solana": [{"address": {"address": "3vmfn3EHsmAaEXpuN6NxfitMnJFCsrUD3NBvXwKjZzjw", "chain": "solana", "arkhamEntity": {"name": "ZeroFi", "note": "", "id": "zerofi", "type": "dex", "service": null, "addresses": null}, "arkhamLabel": {"name": "Vault", "address": "3vmfn3EHsmAaEXpuN6NxfitMnJFCsrUD3NBvXwKjZzjw", "chainType": "solana"}, "isUserAddress": false, "ownerAddress": {"address": "3vmfn3EHsmAaEXpuN6NxfitMnJFCsrUD3NBvXwKjZzjw", "chain": "solana", "arkhamEntity": {"name": "ZeroFi", "note": "", "id": "zerofi", "type": "dex", "service": null, "addresses": null}, "arkhamLabel": {"name": "Vault", "address": "3vmfn3EHsmAaEXpuN6NxfitMnJFCsrUD3NBvXwKjZzjw", "chainType": "solana"}, "isUserAddress": false, "service": false, "program": false}}, "usd": 1937.6297988891602, "transactionCount": 71, "flow": "all", "chains": ["solana"]}, {"address": {"address": "VgwuBBGNCVyT3fnEvRPFhMcYsDN9BH66F6nMQoX9azw", "chain": "solana", "arkhamEntity": {"name": "Orca", "note": "", "id": "orca", "type": "dex", "service": null, "addresses": null, "website": "https://www.orca.so", "twitter": "https://x.com/orca_so"}, "arkhamLabel": {"name": "Pool", "address": "VgwuBBGNCVyT3fnEvRPFhMcYsDN9BH66F6nMQoX9azw", "chainType": "solana"}, "isUserAddress": false, "ownerAddress": {"address": "D6NdKrKNQPmRZCCnG1GqXtF7MMoHB7qR6GU5TkG59Qz1", "chain": "solana", "arkhamEntity": {"name": "Orca", "note": "", "id": "orca", "type": "dex", "service": null, "addresses": null, "website": "https://www.orca.so", "twitter": "https://x.com/orca_so"}, "arkhamLabel": {"name": "Market", "address": "D6NdKrKNQPmRZCCnG1GqXtF7MMoHB7qR6GU5TkG59Qz1", "chainType": "solana"}, "isUserAddress": false, "service": false, "program": false}}, "usd": 1837.5642805099487, "transactionCount": 69, "flow": "all", "chains": ["solana"]}, {"address": {"address": "7UYZ4vX13mmGiopayLZAduo8aie77yZ3o8FMzTeAX8uJ", "chain": "solana", "arkhamEntity": {"name": "Raydium", "note": "", "id": "raydium", "type": "dex", "service": null, "addresses": null, "website": "https://raydium.io", "twitter": "https://twitter.com/RaydiumProtocol"}, "isUserAddress": false, "ownerAddress": {"address": "5Q544fKrFoe6tsEbD7S8EmxGTJYAKtTVhAW5Q5pge4j1", "chain": "solana", "arkhamEntity": {"name": "Raydium", "note": "", "id": "raydium", "type": "dex", "service": null, "addresses": null, "website": "https://raydium.io", "twitter": "https://twitter.com/RaydiumProtocol"}, "arkhamLabel": {"name": "Authority V4", "address": "5Q544fKrFoe6tsEbD7S8EmxGTJYAKtTVhAW5Q5pge4j1", "chainType": "solana"}, "isUserAddress": false, "service": false, "program": false}}, "usd": 133.3408317565918, "transactionCount": 3, "flow": "all", "chains": ["solana"]}, {"address": {"address": "6AKBySNVUyGHsAYHxEpzHsaWnEsf5JZTkGnt3k4zBMhE", "chain": "solana", "arkhamEntity": {"name": "Phoenix", "note": "", "id": "phoenix-trade", "type": "dex", "service": null, "addresses": null, "website": "https://www.phoenix.trade", "twitter": "https://x.com/PhoenixTrade"}, "arkhamLabel": {"name": "Pool", "address": "6AKBySNVUyGHsAYHxEpzHsaWnEsf5JZTkGnt3k4zBMhE", "chainType": "solana"}, "userLabel": {"name": "phoenix trade WIF pool", "address": "6AKBySNVUyGHsAYHxEpzHsaWnEsf5JZTkGnt3k4zBMhE", "chainType": "solana"}, "isUserAddress": false, "ownerAddress": {"address": "6AKBySNVUyGHsAYHxEpzHsaWnEsf5JZTkGnt3k4zBMhE", "chain": "solana", "arkhamEntity": {"name": "Phoenix", "note": "", "id": "phoenix-trade", "type": "dex", "service": null, "addresses": null, "website": "https://www.phoenix.trade", "twitter": "https://x.com/PhoenixTrade"}, "arkhamLabel": {"name": "Pool", "address": "6AKBySNVUyGHsAYHxEpzHsaWnEsf5JZTkGnt3k4zBMhE", "chainType": "solana"}, "isUserAddress": false, "service": false, "program": false}}, "usd": 56.80331802368164, "transactionCount": 3, "flow": "all", "chains": ["solana"]}, {"address": {"address": "8TGUDLeRyzWyfrXLkAvCadWw5EKJwnPCYNinazav76v3", "chain": "solana", "arkhamEntity": {"name": "Orca", "note": "", "id": "orca", "type": "dex", "service": null, "addresses": null, "website": "https://www.orca.so", "twitter": "https://x.com/orca_so"}, "arkhamLabel": {"name": "Pool", "address": "8TGUDLeRyzWyfrXLkAvCadWw5EKJwnPCYNinazav76v3", "chainType": "solana"}, "isUserAddress": false, "ownerAddress": {"address": "6qgyDW4fHvpTAmfNZvPAuETEbVwRKFVAuuHfNzvEmPkY", "chain": "solana", "arkhamEntity": {"name": "Orca", "note": "", "id": "orca", "type": "dex", "service": null, "addresses": null, "website": "https://www.orca.so", "twitter": "https://x.com/orca_so"}, "arkhamLabel": {"name": "Market", "address": "6qgyDW4fHvpTAmfNZvPAuETEbVwRKFVAuuHfNzvEmPkY", "chainType": "solana"}, "isUserAddress": false, "service": false, "program": false}}, "usd": 43.94897747039795, "transactionCount": 3, "flow": "in", "chains": ["solana"]}, {"address": {"address": "28u8R3He2Bm9tvWp1BXHuNfzp7mMWyS73agnWJoLs4Ne", "chain": "solana", "arkhamEntity": {"name": "Orca", "note": "", "id": "orca", "type": "dex", "service": null, "addresses": null, "website": "https://www.orca.so", "twitter": "https://x.com/orca_so"}, "arkhamLabel": {"name": "Pool", "address": "28u8R3He2Bm9tvWp1BXHuNfzp7mMWyS73agnWJoLs4Ne", "chainType": "solana"}, "isUserAddress": false, "ownerAddress": {"address": "56Ekyu6uBpTna3LR2qkjHjNbDNkCLWK2Lt3uWh7J2R8Z", "chain": "solana", "arkhamEntity": {"name": "Orca", "note": "", "id": "orca", "type": "dex", "service": null, "addresses": null, "website": "https://www.orca.so", "twitter": "https://x.com/orca_so"}, "arkhamLabel": {"name": "Market", "address": "56Ekyu6uBpTna3LR2qkjHjNbDNkCLWK2Lt3uWh7J2R8Z", "chainType": "solana"}, "isUserAddress": false, "service": false, "program": false}}, "usd": 20.420747756958008, "transactionCount": 1, "flow": "in", "chains": ["solana"]}]}